{
    "Jana Winderen": [
        {
            "url": "https://janawinderen.bandcamp.com/album/cloitre",
            "title": "Cloitre",
            "artist": "Thomas Köner & Jana Winderen",
            "label": "Touch",
            "band_id": 2093926421,
            "classification": "paid",
            "tags": [
                "Experimental",
                "Oslo"
            ],
            "item_id": 891909707,
            "art_id": 3009534298,
            "is_preorder": false,
            "datePublished": "16 Jun 2017 00:00:00 GMT",
            "about": "Recorded live from the cloisters at Evreux Cathedral, Normandy, France by Franck Dubois, 14th June 2014, as part of L’Ateliers. With thanks to Denis Boyer.",
            "credits": "released June 16, 2017\nRemastered by Thomas Köner\nPhotography by Jon Wozencroft",
            "license": "all rights reserved",
            "coverUrl_0": "https://f4.bcbits.com/img/a3009534298_0",
            "trackinfo": [
                {
                    "title": "Cloitre",
                    "duration": "44:24",
                    "lyrics": null,
                    "label": "Touch",
                    "track_id": 2893040394,
                    "track_num": "1",
                    "artist": "Thomas Köner & Jana Winderen",
                    "url": "https://janawinderen.bandcamp.com/track/cloitre",
                    "trackCoverUrl_0": "https://f4.bcbits.com/img/a3009534298_0",
                    "art_id": 3009534298,
                    "about": null,
                    "credits": "from Cloitre, track released June 16, 2017",
                    "license": "all rights reserved"
                }
            ],
            "archived": true,
            "archived_at": "2026-04-05T01:08:14.903667+00:00",
            "uploaded": true,
            "uploaded_at": "2026-04-05T01:14:52.724154+00:00",
            "pd_wacz_id": "tW2L6yr2"
        },
        {
            "url": "https://janawinderen.bandcamp.com/album/d-bris",
            "title": "Débris",
            "artist": "Jana Winderen",
            "label": "Touch",
            "band_id": 2093926421,
            "classification": "paid",
            "tags": [
                "Experimental",
                "Oslo"
            ],
            "item_id": 3719355525,
            "art_id": 1262560028,
            "is_preorder": false,
            "datePublished": "16 Jun 2012 00:00:00 GMT",
            "about": "Track listing:\n1. Scuttling around in the shallows\n2. Drying out in the sun\nScuttling Around in the Shallows is from the quadrophonic installation of the same name showed at Galerie B-312, Montreal, Canada 8th January - 5th February 2011.\nDrying Out in the Sun is from a four-speaker outdoor public installation at \"Starfield Simulation #36\", Scaniaparken in Malmö, Sweden, 4th September - 2nd October 2011.",
            "credits": "released June 16, 2012",
            "license": "all rights reserved",
            "coverUrl_0": "https://f4.bcbits.com/img/a1262560028_0",
            "trackinfo": [
                {
                    "title": "Scuttling around in the shallows",
                    "duration": "11:22",
                    "lyrics": null,
                    "label": "Touch",
                    "track_id": 1805289203,
                    "track_num": "1",
                    "artist": "Jana Winderen",
                    "url": "https://janawinderen.bandcamp.com/track/scuttling-around-in-the-shallows",
                    "trackCoverUrl_0": "https://f4.bcbits.com/img/a1262560028_0",
                    "art_id": 1262560028,
                    "about": "Scuttling around in the shallows is from the quadrophonic installation of the same name showed at Galerie B-312, Montreal, Canada 8th January - 5th February 2011.",
                    "credits": "from Débris, track released June 16, 2014",
                    "license": "all rights reserved"
                },
                {
                    "title": "Drying out in the sun",
                    "duration": "16:00",
                    "lyrics": null,
                    "label": "Touch",
                    "track_id": 1820731350,
                    "track_num": "2",
                    "artist": "Jana Winderen",
                    "url": "https://janawinderen.bandcamp.com/track/drying-out-in-the-sun",
                    "trackCoverUrl_0": "https://f4.bcbits.com/img/a1262560028_0",
                    "art_id": 1262560028,
                    "about": "Drying out in the sun is from a four-speaker outdoor public installation at \"Starfield Simulation #36\", Scaniaparken in Malmö, Sweden, 4th September - 2nd October 2011.",
                    "credits": "from Débris, track released June 16, 2014",
                    "license": "all rights reserved"
                }
            ],
            "archived": true,
            "archived_at": "2026-04-05T01:08:43.290823+00:00",
            "uploaded": true,
            "uploaded_at": "2026-04-05T01:15:02.718179+00:00",
            "pd_wacz_id": "WKuycSrs"
        },
        {
            "url": "https://janawinderen.bandcamp.com/album/energy-field",
            "title": "Energy Field",
            "artist": "Jana Winderen",
            "label": "Touch",
            "band_id": 2093926421,
            "classification": "paid",
            "tags": [
                "Experimental",
                "Oslo"
            ],
            "item_id": 1642838320,
            "art_id": 3726075994,
            "is_preorder": false,
            "datePublished": "06 Apr 2010 00:00:00 GMT",
            "about": "Artwork & photography by Jon Wozencroft\nMastered by Denis B;ackham\nTrack Listing:\n1. Aquaculture\n2. Isolation/Measurement\n3. Sense of Latent Power\nArmed with four 8011 DPA hydrophones, DPA 4060 omni mics, a Telinga parabolic reflector mic and and a Sound Devices 744T digital hard disk recorder, Jana Winderen studies and records wild places which have a particular importance in our understanding of the complexity and fragility of marine ecosystems.\nThe recordings were made on field trips to the Barents Sea (north of Norway and Russia), Greenland and Norway, deep in crevasses of glaciers, in fjords and in the open ocean. These elements are then edited and layered into a powerful descriptive soundscape. The open spaces of Greenland, northern winds, ravens and dogs in an icy landscape provide the setting for these haunting but dynamic pieces. Sounds of crustaceans, fish such as cod, haddock, herring and pollock recorded as they are hunting, calling for a mate or orientating themselves in their environment, are all included in the mix. The result is a powerful, mesmeric journey into the unseen audio world of the frozen north.",
            "credits": "released April 6, 2010",
            "license": "all rights reserved",
            "coverUrl_0": "https://f4.bcbits.com/img/a3726075994_0",
            "trackinfo": [
                {
                    "title": "Energy Field",
                    "duration": "50:16",
                    "lyrics": null,
                    "label": "Touch",
                    "track_id": 4019210512,
                    "track_num": "1",
                    "artist": "Jana Winderen",
                    "url": "https://janawinderen.bandcamp.com/track/energy-field",
                    "trackCoverUrl_0": "https://f4.bcbits.com/img/a3726075994_0",
                    "art_id": 3726075994,
                    "about": "Track Listing:\n1. Aquaculture 18:00\n2. Isolation/Measurement 12:11\n3. Sense of Latent Power 20:04",
                    "credits": "from Energy Field, released April 6, 2010",
                    "license": "all rights reserved"
                }
            ],
            "archived": true,
            "archived_at": "2026-04-05T01:09:16.701107+00:00",
            "uploaded": true,
            "uploaded_at": "2026-04-05T01:15:11.208317+00:00",
            "pd_wacz_id": "WUAtu6mE"
        },
        {
            "url": "https://janawinderen.bandcamp.com/album/evaporation",
            "title": "Evaporation",
            "artist": "Jana Winderen",
            "label": "Touch",
            "band_id": 2093926421,
            "classification": "paid",
            "tags": [
                "Experimental",
                "Oslo"
            ],
            "item_id": 1354888379,
            "art_id": 3582168161,
            "is_preorder": false,
            "datePublished": "07 Jun 2014 00:00:00 GMT",
            "about": "Evaporation is an archive collection of installation works. The pieces have been decoded and mixed to stereo from their multi-channels sources (where applicable).\nThe pieces here are described in the track information supplied.",
            "credits": "released June 7, 2014",
            "license": "all rights reserved",
            "coverUrl_0": "https://f4.bcbits.com/img/a3582168161_0",
            "trackinfo": [
                {
                    "title": "Evaporation",
                    "duration": "18:38",
                    "lyrics": null,
                    "label": "Touch",
                    "track_id": 19735716,
                    "track_num": "1",
                    "artist": "Jana Winderen",
                    "url": "https://janawinderen.bandcamp.com/track/evaporation",
                    "trackCoverUrl_0": "https://f4.bcbits.com/img/a0978109875_0",
                    "art_id": 978109875,
                    "about": "This track is the soundtrack for Evaporation which was presented as a sound and video installation for TodaysArt Festival, Den Haag (NL), 25th - 26th September 2009. It was curated by Mike Harding and Remco Schuurbiers.\nEvaporation is the slow vaporisation of a liquid and the reverse of condensation. A type of phase transition, it is the process by which molecules in a liquid state (e.g. water) spontaneously become gaseous (e.g. water vapor). Generally, evaporation can be seen by the gradual disappearance of a liquid from a substance when exposed to a significant volume of gas.\nWinderen visited Greenland in July 2007 where she did hydrophone recordings 25 metres under the ice and inside the ice itself.",
                    "credits": "from Evaporation, track released June 16, 2014",
                    "license": "all rights reserved"
                },
                {
                    "title": "Sub Pelagic Voices",
                    "duration": "19:32",
                    "lyrics": null,
                    "label": "Touch",
                    "track_id": 313531273,
                    "track_num": "2",
                    "artist": "Jana Winderen",
                    "url": "https://janawinderen.bandcamp.com/track/sub-pelagic-voices",
                    "trackCoverUrl_0": "https://f4.bcbits.com/img/a0779284976_0",
                    "art_id": 779284976,
                    "about": "Sub-Pelagic Voices is a 17 minute sound piece made for the Sound Art Weekend 'Gerlesborg' as part of the ISCM World New Music Days, 24th - 26th September 2009. Jana was invited by Jesper Eng at The Gerlesborg School of Fine Art. The piece is based on hydrophone (underwater michrophones) recordings made in Bottnafjorden in August 2009, near Gerlesborg in Bohuslän, Sweden.\nSub-Pelagic Voices was also played at Botanic Sounds 2 in Göteborg, Sweden, in October 2009.",
                    "credits": "from Evaporation, track released June 16, 2014",
                    "license": "all rights reserved"
                },
                {
                    "title": "North Atlantic Drift",
                    "duration": "14:00",
                    "lyrics": null,
                    "label": "Touch",
                    "track_id": 3542481919,
                    "track_num": "3",
                    "artist": "Jana Winderen",
                    "url": "https://janawinderen.bandcamp.com/track/north-atlantic-drift",
                    "trackCoverUrl_0": "https://f4.bcbits.com/img/a2589202382_0",
                    "art_id": 2589202382,
                    "about": "This track was played at JunKroom at Urban Guild, Kyoto, Japan on 13th March 2009, curated by Sean Roe. Jana was participating with the sound piece:\n\"North Atlantic Drift\"\n2009\n14:00 min\nThe track is based on recordings Jana made in the Barents Sea on the Marine Institute research ship Johan Hjort, and of decapods, cod, herring, haddock and sea snails from the Norwegian coastline. Recorded with 2 x 8011 DPA hydrophones and 2 x 4060 DPA omnis on a Sound Devices 744T hard disc recorder.",
                    "credits": "from Evaporation, track released June 16, 2014",
                    "license": "all rights reserved"
                }
            ],
            "archived": true,
            "archived_at": "2026-04-05T01:09:55.227057+00:00",
            "uploaded": true,
            "uploaded_at": "2026-04-05T01:15:18.024945+00:00",
            "pd_wacz_id": "66wUojKb"
        },
        {
            "url": "https://janawinderen.bandcamp.com/album/heated",
            "title": "Heated",
            "artist": "Jana Winderen",
            "label": "Touch",
            "band_id": 2093926421,
            "classification": "paid",
            "tags": [
                "Experimental",
                "Oslo"
            ],
            "item_id": 2019809747,
            "art_id": 796005565,
            "is_preorder": false,
            "datePublished": "16 Nov 2008 00:00:00 GMT",
            "about": "Tracklist:\n1. Heated\nLive performance at Super Deluxe, Tokyo, 24th October 2008. Source material recorded with 2 x 8011 DPA hydrophones, 2 x DolphinEAR/PRO hydrophones and 2 x 4060 DPA microphones on a Sound Devices 744T recorder in Greenland, Iceland and Norway.",
            "credits": "released November 16, 2008",
            "license": "all rights reserved",
            "coverUrl_0": "https://f4.bcbits.com/img/a0796005565_0",
            "trackinfo": [
                {
                    "title": "Heated",
                    "duration": "26:18",
                    "lyrics": null,
                    "label": "Touch",
                    "track_id": 2624896557,
                    "track_num": "1",
                    "artist": "Jana Winderen",
                    "url": "https://janawinderen.bandcamp.com/track/heated",
                    "trackCoverUrl_0": "https://f4.bcbits.com/img/a3826908853_0",
                    "art_id": 3826908853,
                    "about": "Live performance at Super Deluxe, Tokyo, 24th October 2008. Source material recorded with 2 x 8011 DPA hydrophones, 2 x DolphinEAR/PRO hydrophones and 2 x 4060 DPA microphones on a Sound Devices 744T recorder in Greenland, Iceland and Norway.",
                    "credits": "from Heated, track released June 16, 2014",
                    "license": "all rights reserved"
                }
            ],
            "archived": true,
            "archived_at": "2026-04-05T01:10:18.635884+00:00",
            "uploaded": true,
            "uploaded_at": "2026-04-05T01:15:27.645929+00:00",
            "pd_wacz_id": "Gbkb3NU1"
        },
        {
            "url": "https://janawinderen.bandcamp.com/album/listening-through-the-dead-zones-excerpt",
            "title": "Listening Through the Dead Zones [excerpt]",
            "artist": "Jana Winderen",
            "label": "Touch",
            "band_id": 2093926421,
            "classification": "nyp",
            "tags": [
                "Experimental",
                "ambient",
                "field recordings",
                "hydrophones",
                "underwater",
                "world weather network",
                "Oslo"
            ],
            "item_id": 956253629,
            "art_id": 3585287716,
            "is_preorder": false,
            "datePublished": "21 Jun 2022 00:00:00 GMT",
            "about": "HME Helsinki Commission 2020\nExcerpt of the IHME Helsinki 2020 Commission “Listening Through the Dead Zones”, a fourteen channel sound installation made in collaboration with Tony Myatt.\nIt took place in August 2021 at the rowing stadium in Töölö, Helsinki overlooking the Baltic Sea.\nThe work has since been shown as part of the exhibition Hydra in St. Petersburg, and the exhibition Geomancers at the Green Roof overlooking the sea at Marina Barrage in Singapore.\nThe composition is made from recordings made by Jana over the last 16 years in underwater sound environments, from the North Pole to the tropic waters of Thailand.\nInterviews related to the installation can be found here:\nwww.ihmehelsinki.fi/en/ihme-project/\nMore images and information can be found on Jana's website:\nwww.janawinderen.com/exhibitions/listening-through-the-dead-zones-commission-for-ihme-helsinki\n[Dead Zones are hypoxic or low in oxygen areas in the world’s oceans and lakes. In the Baltic Sea, where this installation was made, the limit for what you call a dead zone is when the water contains less than 2mg oxygen per litre of water.]",
            "credits": "released June 21, 2022\nMastered by Denis Blackham\nPublished by Touch Music/Fairwood Music (UK) Ltd.",
            "license": "all rights reserved",
            "coverUrl_0": "https://f4.bcbits.com/img/a3585287716_0",
            "trackinfo": [
                {
                    "title": "Listening Through the Dead Zones [excerpt]",
                    "duration": "11:56",
                    "lyrics": null,
                    "label": "Touch",
                    "track_id": 2723496426,
                    "track_num": "1",
                    "artist": "Jana Winderen",
                    "url": "https://janawinderen.bandcamp.com/track/listening-through-the-dead-zones-excerpt",
                    "trackCoverUrl_0": "https://f4.bcbits.com/img/a3585287716_0",
                    "art_id": 3585287716,
                    "about": null,
                    "credits": "from Listening Through the Dead Zones [excerpt], released June 21, 2022",
                    "license": "all rights reserved"
                }
            ],
            "archived": true,
            "archived_at": "2026-04-05T01:10:43.159226+00:00",
            "uploaded": true,
            "uploaded_at": "2026-04-05T01:15:35.291054+00:00",
            "pd_wacz_id": "wBL64ytm"
        },
        {
            "url": "https://janawinderen.bandcamp.com/album/out-of-range",
            "title": "Out of Range",
            "artist": "Jana Winderen",
            "label": "Touch",
            "band_id": 2093926421,
            "classification": "paid",
            "tags": [
                "Experimental",
                "Oslo"
            ],
            "item_id": 708980957,
            "art_id": 544443394,
            "is_preorder": false,
            "datePublished": "06 Apr 2014 00:00:00 GMT",
            "about": "1 track inc pdf booklet and pdf text files\nPerformed, composed and recorded by Jana Winderen\nPhotography by Jon Wozencroft\nTrack listing:\n1. Out of Range\n\"Out of Range\" is an audio work based on ultrasound and echolocation used by bats, dolphins and other creatures who operate beyond the range of human hearing - 'seeing' with sound, or perhaps 'hearing' objects.\nAll sound is invisible; ultrasound is inaudible. Of course, many species have a greater range of hearing than us humans and also more specific and specialised with complex combinations of the different senses… Creatures on both land and under water produce and/or perceive very high sound frequencies. Some species of insects, birds, fish, and mammals can emit and hear ultrasound, used for communications, hunting and orientation. These creatures operate on a different level of perception to us, in an inaudible range above 20kHz...\nMany animals also use the acoustic properties of a space; a bat for example can use the echo from a tower block wall to amplify their calls for mates in the autumn; a toadfish uses the shape of a cave to amplify their calls to protect their habitat. Whales use the different acoustic properties at different depths in the ocean at different pressure levels to send their long distance calls. An astonishing fact about moths is that they have a reflex action with their wings to shut down when they hear the bat echolocation calls… That we reckon that this is so astonishing says something about us….\nThe mix for the piece is based on ultrasound, hydrophone recordings below the water and also of echolocation sound within audible range. The recordings were made in various locations in Central Park and East River in New York, USA, a forest outside Kaliningrad in Russia, Regents Park in London, UK, and various locations in Madeira, Norway, Denmark and Sweden. The ultrasound is time-stretched to bring it into a frequency range audible for human beings.",
            "credits": "released April 6, 2014\nRecordings were made on a Pettersson Ultrasound Detector D1000X, Reson 4032 and DPA 8011 hydrophones and 4060 dpa microphones onto a Sound Devices 477T hard disk recorder.\nThe photographs mirror \"the audible range\" through a contrast between gateways, portals and sight lines, set against situations where the camera eye cannot make sense of the optical event it is confronted with.\nDeutschlandradio Kultur, Redaktion Hörspiel / Klangkunst commissioned the piece for Elektroakustischer Salon: Art’s Birthday 2014, which was performed live at Berghain, Berlin, on Friday 17th January 2014. With thanks to Marcus Gammel.",
            "license": "all rights reserved",
            "coverUrl_0": "https://f4.bcbits.com/img/a0544443394_0",
            "trackinfo": [
                {
                    "title": "Out of Range",
                    "duration": "40:00",
                    "lyrics": null,
                    "label": "Touch",
                    "track_id": 4233537496,
                    "track_num": "1",
                    "artist": "Jana Winderen",
                    "url": "https://janawinderen.bandcamp.com/track/out-of-range",
                    "trackCoverUrl_0": "https://f4.bcbits.com/img/a0544443394_0",
                    "art_id": 544443394,
                    "about": "inc pdf booklet and pdf text files\nPerformed, composed and recorded by Jana Winderen\nPhotography by Jon Wozencroft\n\"Out of Range\" is an audio work based on ultrasound and echolocation used by bats, dolphins and other creatures who operate beyond the range of human hearing - 'seeing' with sound, or perhaps 'hearing' objects.\nAll sound is invisible; ultrasound is inaudible. Of course, many species have a greater range of hearing than us humans and also more specific and specialised with complex combinations of the different senses… Creatures on both land and under water produce and/or perceive very high sound frequencies. Some species of insects, birds, fish, and mammals can emit and hear ultrasound, used for communications, hunting and orientation. These creatures operate on a different level of perception to us, in an inaudible range above 20kHz...\nMany animals also use the acoustic properties of a space; a bat for example can use the echo from a tower block wall to amplify their calls for mates in the autumn; a toadfish uses the shape of a cave to amplify their calls to protect their habitat. Whales use the different acoustic properties at different depths in the ocean at different pressure levels to send their long distance calls. An astonishing fact about moths is that they have a reflex action with their wings to shut down when they hear the bat echolocation calls… That we reckon that this is so astonishing says something about us….\nThe mix for the piece is based on ultrasound, hydrophone recordings below the water and also of echolocation sound within audible range. The recordings were made in various locations in Central Park and East River in New York, USA, a forest outside Kaliningrad in Russia, Regents Park in London, UK, and various locations in Madeira, Norway, Denmark and Sweden. The ultrasound is time-stretched to bring it into a frequency range audible for human beings.",
                    "credits": "from Out of Range, track released June 16, 2014",
                    "license": "all rights reserved"
                }
            ],
            "archived": true,
            "archived_at": "2026-04-05T01:11:09.133350+00:00",
            "uploaded": true,
            "uploaded_at": "2026-04-05T01:15:41.678644+00:00",
            "pd_wacz_id": "PXLD7PQj"
        },
        {
            "url": "https://janawinderen.bandcamp.com/album/pasvikdalen",
            "title": "Pasvikdalen",
            "artist": "Jana Winderen",
            "label": "Touch",
            "band_id": 2093926421,
            "classification": "paid",
            "tags": [
                "Experimental",
                "field recording",
                "hydrophones",
                "Oslo"
            ],
            "item_id": 2230062178,
            "art_id": 221923627,
            "is_preorder": false,
            "datePublished": "10 Oct 2019 00:00:00 GMT",
            "about": "Jana Winderen - Pasvikdalen\nPasvikdalen (2014) was commissioned by Dark Ecology/Sonic Acts/Hilde Methi, performed at the Muziekgebouw, Sonic Acts Festival, Amsterdam and at Kurant, Tromsø (for the Dark Ecology and Arctic Encounter Forum), at NIBIO Svanhovd and at SALT, Oslo\nPhoto by Jana Winderen",
            "credits": "released October 10, 2019\nFull programme:  uit.no/tavla/artikkel/465647/dark_ecology_and_arctic_encounters_forum?p_document_id=465647\nand to the 2014 related field trip to Nikel, Russia:  www.janawinderen.com/fieldtrips/dark_ecology_fieldtrip.html#.XZt1zS2ZPOR\nA stereo version was also played at Svanhovd, Norway, curated for Dark Ecology by Hilde Methi",
            "license": "all rights reserved",
            "coverUrl_0": "https://f4.bcbits.com/img/a0221923627_0",
            "trackinfo": [
                {
                    "title": "Pasvikdalen",
                    "duration": "37:58",
                    "lyrics": null,
                    "label": "Touch",
                    "track_id": 2742370790,
                    "track_num": "1",
                    "artist": "Jana Winderen",
                    "url": "https://janawinderen.bandcamp.com/track/pasvikdalen",
                    "trackCoverUrl_0": "https://f4.bcbits.com/img/a0221923627_0",
                    "art_id": 221923627,
                    "about": null,
                    "credits": "from Pasvikdalen, released October 10, 2019",
                    "license": "all rights reserved"
                }
            ],
            "archived": true,
            "archived_at": "2026-04-05T01:11:37.109330+00:00",
            "uploaded": true,
            "uploaded_at": "2026-04-05T01:15:47.649654+00:00",
            "pd_wacz_id": "GebXQDtq"
        },
        {
            "url": "https://janawinderen.bandcamp.com/album/spring-bloom-in-the-marginal-ice-zone",
            "title": "Spring Bloom in the Marginal Ice Zone",
            "artist": "Jana Winderen",
            "label": "Touch",
            "band_id": 2093926421,
            "classification": "paid",
            "tags": [
                "Experimental",
                "field recordings",
                "hydrophones",
                "Oslo"
            ],
            "item_id": 3602096501,
            "art_id": 1524470346,
            "is_preorder": false,
            "datePublished": "09 Dec 2018 00:00:00 GMT",
            "about": "The listener experiences the bloom of plankton, the shifting and crackling sea ice in the Barents Sea around Spitsbergen (towards the North Pole) and the underwater sounds made by bearded seals, migrating species such as humpbacks and orcas, and the sound of hunting seithe and spawning cod. All depend on the spring bloom.\nIn view of the recent UN Climate Change report, this release is most timely...\nThe marginal ice zone is the dynamic border between the open sea and the sea ice, which is ecologically extremely vulnerable. The phytoplankton present in the sea produces half of the oxygen of the planet. During spring, this zone is the most important CO2 sink in our biosphere. In 'Spring Bloom in the Marginal Ice Zone' the sounds of living creatures become a voice in the current political debate concerning the official definition of the location of the ice edge.",
            "credits": "released December 9, 2018\n'Spring Bloom in the Marginal Ice Zone' is Winderen’s latest instalment in a series of works that reveal the sounds of underwater life, from the warm waters in the Caribbean to the cold and nourishing waters around Greenland, Norway and Iceland. 'Spring Bloom in the Marginal Ice Zone' was a Sonic Acts and Dark Ecology commission supported by Art & Technology — Arts Council Norway, Fond for lyd og bilde, Tono stipendet, ARCEx R/V Helmer Hanssen, University in Tromsø & Foundation Mamont.\nArtwork & photography by Jon Wozencroft\nBooklet photography by Philipp Assmy\nMastered by Denis Blackham, Skye\nPublished by Touch Music/Fairwood Music UK Ltd\nThanks to Paul Wassmann, Carlos Duarte, Britt Kramvig, Berit Kristoffersen, Hilde Methi, Northsailing, Tromsø Friluft Centre, TBA21 Academy.",
            "license": "all rights reserved",
            "coverUrl_0": "https://f4.bcbits.com/img/a1524470346_0",
            "trackinfo": [
                {
                    "title": "Interview with Carlos Duarte",
                    "duration": "05:54",
                    "lyrics": null,
                    "label": "Touch",
                    "track_id": 1494951364,
                    "track_num": "1",
                    "artist": "Jana Winderen",
                    "url": "https://janawinderen.bandcamp.com/track/interview-with-carlos-duarte",
                    "trackCoverUrl_0": "https://f4.bcbits.com/img/a1524470346_0",
                    "art_id": 1524470346,
                    "about": "CARLOS M. DUARTE is Professor of Marine Science, Tarek Ahmed Juffali Research Chair in Red Sea Ecology, Biological and Environmental Science and Engineering Division, and is a world-wide leader in multiple branches of biological oceanography and marine ecology -  www.kaust.edu.sa/en/study/faculty/carlos-duarte",
                    "credits": "from Spring Bloom in the Marginal Ice Zone, released December 9, 2018",
                    "license": "all rights reserved"
                },
                {
                    "title": "Spring Bloom in the Marginal Ice Zone - Headphones Mix",
                    "duration": "36:51",
                    "lyrics": null,
                    "label": "Touch",
                    "track_id": 1728586605,
                    "track_num": "2",
                    "artist": "Jana Winderen",
                    "url": "https://janawinderen.bandcamp.com/track/spring-bloom-in-the-marginal-ice-zone-headphones-mix",
                    "trackCoverUrl_0": "https://f4.bcbits.com/img/a1524470346_0",
                    "art_id": 1524470346,
                    "about": "The marginal ice zone is the dynamic border between the open sea and the sea ice, which is ecologically extremely vulnerable. The phytoplankton present in the sea produces half of the oxygen on the planet. During spring, this zone is the most important CO2 sink in our biosphere. In Spring Bloom in the Marginal Ice Zone the sounds of the living creatures become a voice in the current political debate concerning the official definition of the location of the ice edge.\nThe listener experiences the bloom of plankton, the shifting and crackling sea ice in the Barents Sea around Spitsbergen, towards the North Pole, and the underwater sounds made by bearded seals, migrating species such as humpbacks and orcas, and the sound made by hunting saithe, crustaceans and spawning cod, all depending on the spring bloom.",
                    "credits": "from Spring Bloom in the Marginal Ice Zone, released December 9, 2018",
                    "license": "all rights reserved"
                },
                {
                    "title": "Spring Bloom in the Marginal Ice Zone - Monitor Mix",
                    "duration": "34:59",
                    "lyrics": null,
                    "label": "Touch",
                    "track_id": 1738780956,
                    "track_num": "3",
                    "artist": "Jana Winderen",
                    "url": "https://janawinderen.bandcamp.com/track/spring-bloom-in-the-marginal-ice-zone-monitor-mix",
                    "trackCoverUrl_0": "https://f4.bcbits.com/img/a1524470346_0",
                    "art_id": 1524470346,
                    "about": "The marginal ice zone is the dynamic border between the open sea and the sea ice, which is ecologically extremely vulnerable. The phytoplankton present in the sea produces half of the oxygen on the planet. During spring, this zone is the most important CO2 sink in our biosphere. In Spring Bloom in the Marginal Ice Zone the sounds of the living creatures become a voice in the current political debate concerning the official definition of the location of the ice edge.\nThe listener experiences the bloom of plankton, the shifting and crackling sea ice in the Barents Sea around Spitsbergen, towards the North Pole, and the underwater sounds made by bearded seals, migrating species such as humpbacks and orcas, and the sound made by hunting saithe, crustaceans and spawning cod, all depending on the spring bloom.",
                    "credits": "from Spring Bloom in the Marginal Ice Zone, released December 9, 2018",
                    "license": "all rights reserved"
                }
            ],
            "archived": true,
            "archived_at": "2026-04-05T01:12:29.004016+00:00",
            "uploaded": true,
            "uploaded_at": "2026-04-05T01:16:02.287966+00:00",
            "pd_wacz_id": "hxtMQ6L6"
        },
        {
            "url": "https://janawinderen.bandcamp.com/album/surface-runoff",
            "title": "Surface Runoff",
            "artist": "Jana Winderen",
            "label": "Touch",
            "band_id": 2093926421,
            "classification": "paid",
            "tags": [
                "Experimental",
                "field recordings",
                "Oslo"
            ],
            "item_id": 2674918654,
            "art_id": 3414581401,
            "is_preorder": false,
            "datePublished": "16 Feb 2008 00:00:00 GMT",
            "about": "Originally released as a 7\" vinyl on Autofact Records in 2008",
            "credits": "released February 16, 2008",
            "license": "all rights reserved",
            "coverUrl_0": "https://f4.bcbits.com/img/a3414581401_0",
            "trackinfo": [
                {
                    "title": "Mae Teng",
                    "duration": "02:56",
                    "lyrics": null,
                    "label": "Touch",
                    "track_id": 427808853,
                    "track_num": "1",
                    "artist": "Jana Winderen",
                    "url": "https://janawinderen.bandcamp.com/track/mae-teng",
                    "trackCoverUrl_0": "https://f4.bcbits.com/img/a3414581401_0",
                    "art_id": 3414581401,
                    "about": null,
                    "credits": "from Surface Runoff, track released June 16, 2014\nDesign by Philip Marshall\nCyt by Jason at Transition",
                    "license": "all rights reserved"
                },
                {
                    "title": "Drift",
                    "duration": "04:48",
                    "lyrics": null,
                    "label": "Touch",
                    "track_id": 2279888559,
                    "track_num": "2",
                    "artist": "Jana Winderen",
                    "url": "https://janawinderen.bandcamp.com/track/drift",
                    "trackCoverUrl_0": "https://f4.bcbits.com/img/a3414581401_0",
                    "art_id": 3414581401,
                    "about": null,
                    "credits": "from Surface Runoff, track released June 16, 2014",
                    "license": "all rights reserved"
                }
            ],
            "archived": true,
            "archived_at": "2026-04-05T01:12:58.058869+00:00",
            "uploaded": true,
            "uploaded_at": "2026-04-05T01:16:13.510463+00:00",
            "pd_wacz_id": "EmabAeTa"
        },
        {
            "url": "https://janawinderen.bandcamp.com/album/the-blue-beyond",
            "title": "The Blue Beyond",
            "artist": "Jana Winderen",
            "label": "Touch",
            "band_id": 2093926421,
            "classification": "paid",
            "tags": [
                "Experimental",
                "field recordings",
                "hydrophones",
                "Oslo"
            ],
            "item_id": 1762999512,
            "art_id": 4143384099,
            "is_preorder": false,
            "datePublished": "04 Aug 2023 00:00:00 GMT",
            "about": "The Blue Beyond is produced by Touch and Audemars Piguet following Audemars Piguet Contemporary’s commission of two new compositions by Jana Winderen in 2019.\nEdition of 1000 copies, the first 100 copies numbered and signed by the artist.\nThe record offers edits of two sound compositions for installations, “Du Petit Risoud aux Profondeurs du Lac de Joux” (2019) and “The Art of Listening: Under Water” (2019). “Du Petit Risoud aux Profondeurs du Lac de Joux” was first presented at Art Basel in Basel from 13 to 16 June 2019. A live performance of the piece was given at HEK (House of Electronic Arts Basel) on 11 June 2019. “The Art of Listening: Under Water” (2019) was first presented in the Rotunda, Collins Park, Miami Beach, in the context of Art Basel in Miami Beach, from 4 to 8 December 2019. “The Art of Listening: Under Water” installation was made in collaboration with Tony Myatt. It travelled to the Lenfest Center for the Arts, Columbia University School of the Arts, New York, from 3 to 13 February 2022\nCommissioned by Audemars Piguet Contemporary\nWinderen’s practice focuses on sound and knowledge production. The artist seeks to raise awareness of the environmental issues we face as a society.\nAudemars Piguet Contemporary collaborated with Winderen on two new sound installations compositions. The first, “Du Petit Risoud aux Profondeurs du Lac de Joux”, was developed during two field trips to Le Brassus in the Vallée de Joux, at the heart of the Swiss Jura, where Audemars Piguet has been based since 1875. On these trips, Winderen captured sounds in the waters of the Lac de Joux and in the Risoud forest.\nWhen Audemars Piguet Contemporary invited the artist to present a second composition for exhibition in Miami Beach, Winderen proposed a site-specific sound environment. For “The Art of Listening: Under Water”, Winderen used sounds recorded in the Atlantic Ocean in the Miami area, as well as sounds from the Barents Sea around the North Pole and the Tropical Oceans to expose the constant underwater presence of human-created sound today.\nIn both pieces, the artist offers a unique opportunity to listen closely to the underwater inhabitants of a specific region and to reflect on how human activity interacts and interferes with aquatic and also terrestrial life in a seemingly beautiful and visually calm environment.\nJana Winderen often draws the fish, amphibians and plankton she meets. This release also consists of a drawing of two fish that probably would never meet; the pike from the freshwater Lac de Joux in the Jura Mountains and the snapper from the saltwater environment by Miami.\nAbout Audemars Piguet Contemporary\nAudemars Piguet Contemporary supports contemporary artists who wish to explore a new direction in their practice, providing them with a platform to evolve creatively through a commission. Audemars Piguet\nContemporary’s team of in-house curators support the artist along each step of the commission, from inception to development to exhibition, giving artists the freedom to experiment and develop a work that might not have been otherwise possible. The resulting artworks belong to the artists and contribute to their body of work.",
            "credits": "released August 4, 2023\nAll tracks composed by Jana Winderen\nMastered and cut by Jason at Transition\nArtwork & photography by Jon Wozencroft\nPublished by Touch Music/Fairwood Music (UK) Ltd.\nCommissioned by Audemars Piguet Contemporary\n℗ & © 2023 Audemars Piguet/Touch",
            "license": "all rights reserved",
            "coverUrl_0": "https://f4.bcbits.com/img/a4143384099_0",
            "trackinfo": [
                {
                    "title": "The Art of Listening: Under Water",
                    "duration": "16:59",
                    "lyrics": null,
                    "label": "Touch",
                    "track_id": 2751094503,
                    "track_num": "1",
                    "artist": "Jana Winderen",
                    "url": "https://janawinderen.bandcamp.com/track/the-art-of-listening-under-water",
                    "trackCoverUrl_0": "https://f4.bcbits.com/img/a4143384099_0",
                    "art_id": 4143384099,
                    "about": null,
                    "credits": "from The Blue Beyond, released August 4, 2023",
                    "license": "all rights reserved"
                },
                {
                    "title": "Du Petit Risoud  aux Profondeurs du Lac de Joux",
                    "duration": "15:23",
                    "lyrics": null,
                    "label": "Touch",
                    "track_id": 1630025365,
                    "track_num": "2",
                    "artist": "Jana Winderen",
                    "url": "https://janawinderen.bandcamp.com/track/du-petit-risoud-aux-profondeurs-du-lac-de-joux",
                    "trackCoverUrl_0": "https://f4.bcbits.com/img/a4143384099_0",
                    "art_id": 4143384099,
                    "about": null,
                    "credits": "from The Blue Beyond, released August 4, 2023",
                    "license": "all rights reserved"
                }
            ],
            "archived": true,
            "archived_at": "2026-04-05T01:13:28.858479+00:00",
            "uploaded": true,
            "uploaded_at": "2026-04-05T01:16:22.698443+00:00",
            "pd_wacz_id": "je6uHd5g"
        },
        {
            "url": "https://janawinderen.bandcamp.com/album/the-listener",
            "title": "The Listener",
            "artist": "Jana Winderen",
            "label": "Touch",
            "band_id": 2093926421,
            "classification": "paid",
            "tags": [
                "Experimental",
                "Oslo"
            ],
            "item_id": 3823057953,
            "art_id": 4241659183,
            "is_preorder": false,
            "datePublished": "04 Dec 2016 00:00:00 GMT",
            "about": "Track listing:\n1. The Listener\nIllustration by Jana Winderen. Designed in October 2016 by Philip Marshall.\nFreshwater biologists count underwater insects and use this data as an indicator of the water's health. If one identifies the sound of specific underwater insects with their varying ability to survive forms of pollution, one can possibly, through focused listening, reach an understanding of the health of the river. Underwater insects use stridulation to produce sound, such as Corixa, the lesser water boatman, which lives its whole life underwater. It also uses an air bubble carried on its abdomen as a physical lung, where oxygen flows from the water into the bubble. This bubble might also be amplifying the sound they make.\nThe Listener is a sound composition created from hydrophone recordings in the River Orne in Normandy. A 6 channel sound installation made for the exhibition 'Second Nature' is part of a 3 year investigation into the health of the river.",
            "credits": "released December 4, 2016\nPublished by Touch Music/Fairwood Music UK Ltd. Production ésam Caen / Cherbourg.",
            "license": "all rights reserved",
            "coverUrl_0": "https://f4.bcbits.com/img/a4241659183_0",
            "trackinfo": [
                {
                    "title": "The Listener",
                    "duration": "22:58",
                    "lyrics": null,
                    "label": "Touch",
                    "track_id": 1472285851,
                    "track_num": "1",
                    "artist": "Jana Winderen",
                    "url": "https://janawinderen.bandcamp.com/track/the-listener",
                    "trackCoverUrl_0": "https://f4.bcbits.com/img/a4241659183_0",
                    "art_id": 4241659183,
                    "about": null,
                    "credits": "from The Listener, released December 4, 2016",
                    "license": "all rights reserved"
                }
            ],
            "archived": true,
            "archived_at": "2026-04-05T01:13:51.840178+00:00",
            "uploaded": true,
            "uploaded_at": "2026-04-05T01:16:31.881628+00:00",
            "pd_wacz_id": "3CFv791V"
        },
        {
            "url": "https://janawinderen.bandcamp.com/album/the-noisiest-guys-on-the-planet",
            "title": "The Noisiest Guys on the Planet",
            "artist": "Jana Winderen",
            "label": "Touch",
            "band_id": 2093926421,
            "classification": "paid",
            "tags": [
                "Experimental",
                "field recordings",
                "hydrophones",
                "Oslo"
            ],
            "item_id": 2123273444,
            "art_id": 2139066376,
            "is_preorder": false,
            "datePublished": "08 Oct 2009 00:00:00 GMT",
            "about": null,
            "credits": "released October 8, 2009\nDrawing by Jana Winderen\nThanks to: Institute of Marine Research and the crew on Johan Hjort.\nP & C with a circle MMIX Ash International - \"requiescat in sonitus.\"",
            "license": "all rights reserved",
            "coverUrl_0": "https://f4.bcbits.com/img/a2139066376_0",
            "trackinfo": [
                {
                    "title": "The Noisiest Guys on the Planet 1",
                    "duration": "19:13",
                    "lyrics": null,
                    "label": "Touch",
                    "track_id": 1237416376,
                    "track_num": "1",
                    "artist": "Jana Winderen",
                    "url": "https://janawinderen.bandcamp.com/track/the-noisiest-guys-on-the-planet-1",
                    "trackCoverUrl_0": "https://f4.bcbits.com/img/a2139066376_0",
                    "art_id": 2139066376,
                    "about": null,
                    "credits": "from The Noisiest Guys on the Planet, released October 8, 2009",
                    "license": "all rights reserved"
                }
            ],
            "archived": true,
            "archived_at": "2026-04-05T01:14:18.890161+00:00",
            "uploaded": true,
            "uploaded_at": "2026-04-05T01:16:37.684024+00:00",
            "pd_wacz_id": "1c4VuTsc"
        },
        {
            "url": "https://janawinderen.bandcamp.com/album/the-wanderer",
            "title": "The Wanderer",
            "artist": "Jana Winderen",
            "label": "Touch",
            "band_id": 2093926421,
            "classification": "paid",
            "tags": [
                "Experimental",
                "field recordings",
                "hydrophones",
                "Oslo"
            ],
            "item_id": 3600818392,
            "art_id": 4256761762,
            "is_preorder": false,
            "datePublished": "09 Feb 2016 00:00:00 GMT",
            "about": "Zooplankton and Phytoplankton are organisms which drift in the oceans, seas and bodies of fresh water. The word ‘zooplankton’ is derived from the Greek zoon (ζῴον), meaning ‘animal’, phyto is derived from the Greek words φυτόν (phyton), meaning plant and planktos (πλαγκτός), meaning wanderer or drifter.\nMammals, fish and crustaceans feed on zooplankton and they in turn feed on phytoplankton. Phytoplankton need two things for photosynthesis and thus their survival: energy from the sun and nutrients from the water. In the process of photosynthesis, phytoplankton release oxygen into the water. Half of the world's oxygen is produced by phytoplankton photosynthesis.\nLocal abundance varies horizontally in the water column, vertically with ocean drifts and seasonally with the light.\nThe Wanderer is a sound composition created from hydrophone recordings from the realm of these creatures in the Atlantic Ocean, made by Jana on her travels from the North Pole to the Equator.\nThe Wanderer was produced for the Lorch Schive Art Prize, Trondheim Kunstmuseum in 2015.\nambientblog.net  writes:\n\"Damn those extremely limited releases!! I cursed myself for missing the original release of this work: a beautiful 4Gb USB credit card that also included a surround (quad) version of this piece that was originally produced for a 16-channel installation. So I’ll have to do with the stereo version – which is so perfectly recorded that is is totally immersive too.\nThese field recordings may sound like a collection of strange animals, weird insects, wind, rain and an occasional drone sound. But sounds are deceiving: these sounds are hydrophone recordings from the Atlantic Ocean, from the realms of Zooplankton and Phytoplankton.\nIt would be interesting to know more about how exactly these recordings were made (how does one record the sound of Plankton?), but that detailed information is not included here.\nPlankton comes from the Greek word Planktos, which means wanderer or drifter. Its importance can hardly be overrated:\n‘Mammals, fish and crustaceans feed on zooplankton and they in turn feed on phytoplankton. Phytoplankton need two things for photosynthesis and thus their survival: energy from the sun and nutrients from the water. In the process of photosynthesis, phytoplankton release oxygen into the water. Half of the world’s oxygen is produced by phytoplankton photosynthesis.’\nHalf of the world’s oxygen! With this 40 minute piece of ‘field’ recordings, Jana Winderen has created an impressive sonic monument celebrating the organisms at the very root of our existence!\"",
            "credits": "released February 9, 2016",
            "license": "all rights reserved",
            "coverUrl_0": "https://f4.bcbits.com/img/a4256761762_0",
            "trackinfo": [
                {
                    "title": "The Wanderer",
                    "duration": "31:21",
                    "lyrics": null,
                    "label": "Touch",
                    "track_id": 1743642157,
                    "track_num": "1",
                    "artist": "Jana Winderen",
                    "url": "https://janawinderen.bandcamp.com/track/the-wanderer-2",
                    "trackCoverUrl_0": "https://f4.bcbits.com/img/a4256761762_0",
                    "art_id": 4256761762,
                    "about": "Zooplankton and Phytoplankton are organisms which drift in the oceans, seas and bodies of fresh water. The word ‘zooplankton’ is derived from the Greek zoon (ζῴον), meaning ‘animal’, phyto is derived from the Greek words φυτόν (phyton), meaning plant and planktos (πλαγκτός), meaning wanderer or drifter.\nMammals, fish and crustaceans feed on zooplankton and they in turn feed on phytoplankton. Phytoplankton need two things for photosynthesis and thus their survival: energy from the sun and nutrients from the water. In the process of photosynthesis, phytoplankton release oxygen into the water. Half of the world's oxygen is produced by phytoplankton photosynthesis.\nLocal abundance varies horizontally in the water column, vertically with ocean drifts and seasonally with the light.\nThe Wanderer is a sound composition created from hydrophone recordings from the realm of these creatures in the Atlantic Ocean, made by Jana on her travels from the North Pole to the Equator.\nThe Wanderer was produced for the Lorch Schive Art Prize, Trondheim Kunstmuseum in 2015.",
                    "credits": "from The Wanderer, released February 9, 2016",
                    "license": "all rights reserved"
                }
            ],
            "archived": true,
            "archived_at": "2026-04-05T01:14:45.098262+00:00",
            "uploaded": true,
            "uploaded_at": "2026-04-05T01:16:43.335703+00:00",
            "pd_wacz_id": "PxM6fS3Y"
        }
    ],
    "_band_id": 2093926421
}