{
    "Axel Dörner": [
        {
            "url": "https://axeldoerner.bandcamp.com/album/afore-2",
            "title": "afore",
            "artist": "Seijiro Murayama / Axel Dörner",
            "label": null,
            "band_id": 1365097893,
            "classification": "paid",
            "tags": [
                "Jazz"
            ],
            "item_id": 526851594,
            "art_id": 2074798423,
            "is_preorder": false,
            "datePublished": "10 Aug 2024 15:19:08 GMT",
            "about": "Seijiro Murayama - voice, percussion\nAxel Dörner - trumpet, electronics\nrecorded 11th of August 2022 at sowieso in Berlin, Germany\nmixed and mastered by Axel Dörner\nvideo (excerpt) by Carina Khorkhordina:\nvimeo.com/839726092",
            "credits": "released August 10, 2024",
            "license": "all rights reserved",
            "coverUrl_0": "https://f4.bcbits.com/img/a2074798423_0",
            "trackinfo": [
                {
                    "title": "afore",
                    "duration": "40:56",
                    "lyrics": null,
                    "label": null,
                    "track_id": 3896518189,
                    "track_num": "1",
                    "artist": "Seijiro Murayama / Axel Dörner",
                    "url": "https://axeldoerner.bandcamp.com/track/afore",
                    "trackCoverUrl_0": "https://f4.bcbits.com/img/a2033607722_0",
                    "art_id": 2033607722,
                    "about": "Seijiro Murayama - voice, percussion\nAxel Dörner - trumpet, electronics\nrecorded 11th of August 2022 in Berlin at sowieso\nmixed and mastered by Axel Dörner\nlive video (excerpt) by Carina Khorkhordina:\nvimeo.com/839726092",
                    "credits": "from afore, released August 10, 2024",
                    "license": "all rights reserved"
                }
            ]
        },
        {
            "url": "https://axeldoerner.bandcamp.com/album/br-nsh-j",
            "title": "brønshøj",
            "artist": "Axel Dörner",
            "label": null,
            "band_id": 1365097893,
            "classification": "paid",
            "tags": [
                "Jazz"
            ],
            "item_id": 2468365552,
            "art_id": 777026810,
            "is_preorder": false,
            "datePublished": "31 Aug 2022 00:00:00 GMT",
            "about": "Axel Dörner - trumpet, electronics\nrecorded 3rd of July 2022 in Copenhagen, Denmark",
            "credits": "released August 31, 2022",
            "license": "all rights reserved",
            "coverUrl_0": "https://f4.bcbits.com/img/a0777026810_0",
            "trackinfo": [
                {
                    "title": "brønshøj",
                    "duration": "19:22",
                    "lyrics": null,
                    "label": null,
                    "track_id": 3704070253,
                    "track_num": "1",
                    "artist": "Axel Dörner",
                    "url": "https://axeldoerner.bandcamp.com/track/br-nsh-j",
                    "trackCoverUrl_0": "https://f4.bcbits.com/img/a0777026810_0",
                    "art_id": 777026810,
                    "about": null,
                    "credits": "from brønshøj, released August 31, 2022",
                    "license": "all rights reserved"
                }
            ]
        },
        {
            "url": "https://axeldoerner.bandcamp.com/album/brixia",
            "title": "brixia",
            "artist": "Axel Dörner",
            "label": null,
            "band_id": 1365097893,
            "classification": "paid",
            "tags": [
                "Jazz"
            ],
            "item_id": 3670250702,
            "art_id": 1279662443,
            "is_preorder": false,
            "datePublished": "31 Aug 2022 00:00:00 GMT",
            "about": "Axel Dörner - trumpet, electronics\nrecorded 13th of March 2022 in Brescia, Italy",
            "credits": "released August 31, 2022",
            "license": "all rights reserved",
            "coverUrl_0": "https://f4.bcbits.com/img/a1279662443_0",
            "trackinfo": [
                {
                    "title": "brixia",
                    "duration": "29:36",
                    "lyrics": null,
                    "label": null,
                    "track_id": 465507619,
                    "track_num": "1",
                    "artist": "Axel Dörner",
                    "url": "https://axeldoerner.bandcamp.com/track/brixia",
                    "trackCoverUrl_0": "https://f4.bcbits.com/img/a1279662443_0",
                    "art_id": 1279662443,
                    "about": "Axel Dörner - trumpet, electronics\nrecorded 13th of March 2022 in Brescia, Italy",
                    "credits": "from brixia, released August 31, 2022",
                    "license": "all rights reserved"
                }
            ]
        },
        {
            "url": "https://axeldoerner.bandcamp.com/album/disversicht",
            "title": "disversicht",
            "artist": "Axel Dörner",
            "label": null,
            "band_id": 1365097893,
            "classification": "paid",
            "tags": [
                "Jazz"
            ],
            "item_id": 3758662682,
            "art_id": 1895086962,
            "is_preorder": false,
            "datePublished": "10 Apr 2020 17:29:16 GMT",
            "about": "Axel Dörner trumpet\nrecorded in Berlin March 2020",
            "credits": "released April 10, 2020\nAxel Dörner",
            "license": "all rights reserved",
            "coverUrl_0": "https://f4.bcbits.com/img/a1895086962_0",
            "trackinfo": [
                {
                    "title": "1. ……. 14.43",
                    "duration": "14:43",
                    "lyrics": null,
                    "label": null,
                    "track_id": 3339601884,
                    "track_num": "1",
                    "artist": "Axel Dörner",
                    "url": "https://axeldoerner.bandcamp.com/track/1-1443",
                    "trackCoverUrl_0": "https://f4.bcbits.com/img/a1895086962_0",
                    "art_id": 1895086962,
                    "about": "Axel Dörner trumpet\nrecorded in Berlin March 2020",
                    "credits": "from disversicht, released April 10, 2020",
                    "license": "all rights reserved"
                },
                {
                    "title": "2. ……. 20.19",
                    "duration": "20:18",
                    "lyrics": null,
                    "label": null,
                    "track_id": 3277530381,
                    "track_num": "2",
                    "artist": "Axel Dörner",
                    "url": "https://axeldoerner.bandcamp.com/track/2-2019",
                    "trackCoverUrl_0": "https://f4.bcbits.com/img/a3086357903_0",
                    "art_id": 3086357903,
                    "about": "Axel Dörner trumpet\nrecorded in Berlin March 2020",
                    "credits": "from disversicht, released April 10, 2020\nAxel Dörner",
                    "license": "all rights reserved"
                },
                {
                    "title": "3. ……. 10.19",
                    "duration": "10:18",
                    "lyrics": null,
                    "label": null,
                    "track_id": 3048645194,
                    "track_num": "3",
                    "artist": "Axel Dörner",
                    "url": "https://axeldoerner.bandcamp.com/track/3-1019",
                    "trackCoverUrl_0": "https://f4.bcbits.com/img/a3217530958_0",
                    "art_id": 3217530958,
                    "about": "Axel Dörner trumpet\nrecorded in Berlin March 2020",
                    "credits": "from disversicht, released April 10, 2020\nAxel Dörner",
                    "license": "all rights reserved"
                }
            ]
        },
        {
            "url": "https://axeldoerner.bandcamp.com/album/duo-chandos",
            "title": "Duo Chandos",
            "artist": "Seijiro Murayama, Axel Dörner",
            "label": null,
            "band_id": 1365097893,
            "classification": "paid",
            "tags": [
                "Jazz"
            ],
            "item_id": 2370149763,
            "art_id": 2239864353,
            "is_preorder": false,
            "datePublished": "10 Apr 2020 00:00:00 GMT",
            "about": "Seijiro Murayama voice\nAxel Dörner trumpet\nrecorded 4th of March 2018 in Berlin\nmixed and mastered by Axel Dörner\nproduced by Seijiro Murayama and Axel Dörner",
            "credits": "released April 10, 2020\nSeijiro Murayama, Axel Dörner",
            "license": "all rights reserved",
            "coverUrl_0": "https://f4.bcbits.com/img/a2239864353_0",
            "trackinfo": [
                {
                    "title": "1. ...............14.52",
                    "duration": "14:52",
                    "lyrics": null,
                    "label": null,
                    "track_id": 3519192258,
                    "track_num": "1",
                    "artist": "Seijiro Murayama, Axel Dörner",
                    "url": "https://axeldoerner.bandcamp.com/track/1-1452",
                    "trackCoverUrl_0": "https://f4.bcbits.com/img/a2239864353_0",
                    "art_id": 2239864353,
                    "about": "Seijiro Murayama voice\nAxel Dörner trumpet\nrecorded 4th of March 2018 in Berlin\nmixed and mastered by Axel Dörner\nproduced by Seijiro Murayama and Axel Dörner",
                    "credits": "from Duo Chandos, released April 10, 2020\nSeijiro Murayama, Axel Dörner",
                    "license": "all rights reserved"
                },
                {
                    "title": "2. ...............15.24",
                    "duration": "15:24",
                    "lyrics": null,
                    "label": null,
                    "track_id": 2370888390,
                    "track_num": "2",
                    "artist": "Seijiro Murayama, Axel Dörner",
                    "url": "https://axeldoerner.bandcamp.com/track/2-1524",
                    "trackCoverUrl_0": "https://f4.bcbits.com/img/a2239864353_0",
                    "art_id": 2239864353,
                    "about": "Seijiro Murayama voice\nAxel Dörner trumpet\nrecorded 4th of March 2018 in Berlin\nmixed and mastered by Axel Dörner\nproduced by Seijiro Murayama and Axel Dörner",
                    "credits": "from Duo Chandos, released April 10, 2020\nSeijiro Murayama, Axel Dörner",
                    "license": "all rights reserved"
                },
                {
                    "title": "3. ...............08.59",
                    "duration": "08:59",
                    "lyrics": null,
                    "label": null,
                    "track_id": 3947588894,
                    "track_num": "3",
                    "artist": "Seijiro Murayama, Axel Dörner",
                    "url": "https://axeldoerner.bandcamp.com/track/3-0859",
                    "trackCoverUrl_0": "https://f4.bcbits.com/img/a2239864353_0",
                    "art_id": 2239864353,
                    "about": "Seijiro Murayama voice\nAxel Dörner trumpet\nrecorded 4th of March 2018 in Berlin\nmixed and mastered by Axel Dörner\nproduced by Seijiro Murayama and Axel Dörner",
                    "credits": "from Duo Chandos, released April 10, 2020\nSeijiro Murayama, Axel Dörner",
                    "license": "all rights reserved"
                }
            ]
        },
        {
            "url": "https://axeldoerner.bandcamp.com/album/jakot",
            "title": "Jakot",
            "artist": "Axel Dörner / Pierre-Antoine Badaroux / Pat Thomas / Joel Grip / Antonin Gerbal",
            "label": null,
            "band_id": 1365097893,
            "classification": "paid",
            "tags": [
                "Jazz"
            ],
            "item_id": 2853536387,
            "art_id": 1042500087,
            "is_preorder": false,
            "datePublished": "03 Aug 2023 22:43:46 GMT",
            "about": "Axel Dörner — trumpet, electronics\nPierre-Antoine Badaroux — alto saxophone\nPat Thomas — piano, electronics\nJoel Grip — bass\nAntonin Gerbal — drums\nall compositions by Axel Dörner\nrecorded live 29.06.2019 at Au Topsi Pohl in Berlin, Germany\nmixed and mastered in January 2023 by Axel Dörner",
            "credits": "released August 3, 2023",
            "license": "all rights reserved",
            "coverUrl_0": "https://f4.bcbits.com/img/a1042500087_0",
            "trackinfo": [
                {
                    "title": "background beneath",
                    "duration": "08:26",
                    "lyrics": null,
                    "label": null,
                    "track_id": 2707757817,
                    "track_num": "1",
                    "artist": "Axel Dörner / Pierre-Antoine Badaroux / Pat Thomas / Joel Grip / Antonin Gerbal",
                    "url": "https://axeldoerner.bandcamp.com/track/background-beneath",
                    "trackCoverUrl_0": "https://f4.bcbits.com/img/a1042500087_0",
                    "art_id": 1042500087,
                    "about": "Axel Dörner — trumpet, electronics\nPierre-Antoine Badaroux — alto saxophone\nPat Thomas — piano, electronics\nJoel Grip — bass\nAntonin Gerbal — drums\nrecorded live 29.06.2019 at Au Topsi Pohl in Berlin, Germany\nmixed and mastered in January 2023 by Axel Dörner",
                    "credits": "from Jakot, released August 3, 2023",
                    "license": "all rights reserved"
                },
                {
                    "title": "fälschlich",
                    "duration": "06:21",
                    "lyrics": null,
                    "label": null,
                    "track_id": 1609162724,
                    "track_num": "2",
                    "artist": "Axel Dörner / Pierre-Antoine Badaroux / Pat Thomas / Joel Grip / Antonin Gerbal",
                    "url": "https://axeldoerner.bandcamp.com/track/f-lschlich",
                    "trackCoverUrl_0": "https://f4.bcbits.com/img/a1042500087_0",
                    "art_id": 1042500087,
                    "about": "Axel Dörner — trumpet, electronics\nPierre-Antoine Badaroux — alto saxophone\nPat Thomas — piano, electronics\nJoel Grip — bass\nAntonin Gerbal — drums\nrecorded live 29.06.2019 at Au Topsi Pohl in Berlin, Germany\nmixed and mastered in January 2023 by Axel Dörner",
                    "credits": "from Jakot, released August 3, 2023",
                    "license": "all rights reserved"
                },
                {
                    "title": "schneller - langsamer",
                    "duration": "14:21",
                    "lyrics": null,
                    "label": null,
                    "track_id": 1770825285,
                    "track_num": "3",
                    "artist": "Axel Dörner / Pierre-Antoine Badaroux / Pat Thomas / Joel Grip / Antonin Gerbal",
                    "url": "https://axeldoerner.bandcamp.com/track/schneller-langsamer",
                    "trackCoverUrl_0": "https://f4.bcbits.com/img/a1042500087_0",
                    "art_id": 1042500087,
                    "about": "Axel Dörner — trumpet, electronics\nPierre-Antoine Badaroux — alto saxophone\nPat Thomas — piano, electronics\nJoel Grip — bass\nAntonin Gerbal — drums\nrecorded live 29.06.2019 at Au Topsi Pohl in Berlin, Germany\nmixed and mastered in January 2023 by Axel Dörner",
                    "credits": "from Jakot, released August 3, 2023",
                    "license": "all rights reserved"
                },
                {
                    "title": "ausgekannt",
                    "duration": "06:41",
                    "lyrics": null,
                    "label": null,
                    "track_id": 3469372670,
                    "track_num": "4",
                    "artist": "Axel Dörner / Pierre-Antoine Badaroux / Pat Thomas / Joel Grip / Antonin Gerbal",
                    "url": "https://axeldoerner.bandcamp.com/track/ausgekannt",
                    "trackCoverUrl_0": "https://f4.bcbits.com/img/a1042500087_0",
                    "art_id": 1042500087,
                    "about": "Axel Dörner — trumpet, electronics\nPierre-Antoine Badaroux — alto saxophone\nPat Thomas — piano, electronics\nJoel Grip — bass\nAntonin Gerbal — drums\nrecorded live 29.06.2019 at Au Topsi Pohl in Berlin, Germany\nmixed and mastered in January 2023 by Axel Dörner",
                    "credits": "from Jakot, released August 3, 2023",
                    "license": "all rights reserved"
                },
                {
                    "title": "viaduct",
                    "duration": "11:58",
                    "lyrics": null,
                    "label": null,
                    "track_id": 2310848701,
                    "track_num": "5",
                    "artist": "Axel Dörner / Pierre-Antoine Badaroux / Pat Thomas / Joel Grip / Antonin Gerbal",
                    "url": "https://axeldoerner.bandcamp.com/track/viaduct",
                    "trackCoverUrl_0": "https://f4.bcbits.com/img/a1042500087_0",
                    "art_id": 1042500087,
                    "about": "Axel Dörner — trumpet, electronics\nPierre-Antoine Badaroux — alto saxophone\nPat Thomas — piano, electronics\nJoel Grip — bass\nAntonin Gerbal — drums\nrecorded live 29.06.2019 at Au Topsi Pohl in Berlin, Germany\nmixed and mastered in January 2023 by Axel Dörner",
                    "credits": "from Jakot, released August 3, 2023",
                    "license": "all rights reserved"
                },
                {
                    "title": "hereich",
                    "duration": "10:51",
                    "lyrics": null,
                    "label": null,
                    "track_id": 1074768813,
                    "track_num": "6",
                    "artist": "Axel Dörner / Pierre-Antoine Badaroux / Pat Thomas / Joel Grip / Antonin Gerbal",
                    "url": "https://axeldoerner.bandcamp.com/track/hereich",
                    "trackCoverUrl_0": "https://f4.bcbits.com/img/a1042500087_0",
                    "art_id": 1042500087,
                    "about": "Axel Dörner — trumpet, electronics\nPierre-Antoine Badaroux — alto saxophone\nPat Thomas — piano, electronics\nJoel Grip — bass\nAntonin Gerbal — drums\nrecorded live 29.06.2019 at Au Topsi Pohl in Berlin, Germany\nmixed and mastered in January 2023 by Axel Dörner",
                    "credits": "from Jakot, released August 3, 2023",
                    "license": "all rights reserved"
                }
            ]
        },
        {
            "url": "https://axeldoerner.bandcamp.com/album/magado",
            "title": "magado",
            "artist": "Axel Dörner",
            "label": null,
            "band_id": 1365097893,
            "classification": "paid",
            "tags": [
                "Jazz"
            ],
            "item_id": 2352472822,
            "art_id": 1605598304,
            "is_preorder": false,
            "datePublished": "31 Aug 2022 00:00:00 GMT",
            "about": "Axel Dörner - trumpet, electronics\nrecorded 3rd of May 2022 in Magdeburg, Germany",
            "credits": "released August 31, 2022",
            "license": "all rights reserved",
            "coverUrl_0": "https://f4.bcbits.com/img/a1605598304_0",
            "trackinfo": [
                {
                    "title": "magado",
                    "duration": "21:48",
                    "lyrics": null,
                    "label": null,
                    "track_id": 191803557,
                    "track_num": "1",
                    "artist": "Axel Dörner",
                    "url": "https://axeldoerner.bandcamp.com/track/magado",
                    "trackCoverUrl_0": "https://f4.bcbits.com/img/a1605598304_0",
                    "art_id": 1605598304,
                    "about": null,
                    "credits": "from magado, released August 31, 2022",
                    "license": "all rights reserved"
                }
            ]
        },
        {
            "url": "https://axeldoerner.bandcamp.com/album/mohabit-2753",
            "title": "mohabit 27.53",
            "artist": "Axel Dörner",
            "label": null,
            "band_id": 1365097893,
            "classification": "paid",
            "tags": [
                "Jazz",
                "electronic music"
            ],
            "item_id": 1386020782,
            "art_id": 3087482209,
            "is_preorder": false,
            "datePublished": "10 Jan 2025 00:00:00 GMT",
            "about": "Axel Dörner - trumpet, electronics\nrecorded live 09.06.2023 at PAS, Berlin, Germany",
            "credits": "released January 10, 2025\nAxel Dörner",
            "license": "all rights reserved",
            "coverUrl_0": "https://f4.bcbits.com/img/a3087482209_0",
            "trackinfo": [
                {
                    "title": "mohabit 27.53",
                    "duration": "27:52",
                    "lyrics": null,
                    "label": null,
                    "track_id": 660606376,
                    "track_num": "1",
                    "artist": "Axel Dörner",
                    "url": "https://axeldoerner.bandcamp.com/track/mohabit-2753",
                    "trackCoverUrl_0": "https://f4.bcbits.com/img/a3087482209_0",
                    "art_id": 3087482209,
                    "about": "Axel Dörner - trumpet, electronics\nrecorded 09.06.2023 live at PAS, Berlin, Germany",
                    "credits": "from mohabit 27.53, released January 10, 2025\nAxel Dörner",
                    "license": "all rights reserved"
                }
            ]
        },
        {
            "url": "https://axeldoerner.bandcamp.com/album/sicherlich-2",
            "title": "sicherlich",
            "artist": "Axel Dörner",
            "label": null,
            "band_id": 1365097893,
            "classification": "paid",
            "tags": [
                "Jazz"
            ],
            "item_id": 2219633685,
            "art_id": 4196494041,
            "is_preorder": false,
            "datePublished": "03 Jul 2020 15:02:45 GMT",
            "about": "Axel Dörner trumpet, electronics\nrecorded 24th of June in Berlin\nfor RUIDO+TVL STREAM FEST  (www.tvlrec.com)",
            "credits": "released July 3, 2020",
            "license": "all rights reserved",
            "coverUrl_0": "https://f4.bcbits.com/img/a4196494041_0",
            "trackinfo": [
                {
                    "title": "sicherlich",
                    "duration": "21:23",
                    "lyrics": null,
                    "label": null,
                    "track_id": 1786024273,
                    "track_num": "1",
                    "artist": "Axel Dörner",
                    "url": "https://axeldoerner.bandcamp.com/track/sicherlich",
                    "trackCoverUrl_0": "https://f4.bcbits.com/img/a4196494041_0",
                    "art_id": 4196494041,
                    "about": "Axel Dörner trumpet, electronics\nrecorded 24th of June in Berlin\nfor RUIDO+TVL STREAM FEST  (www.tvlrec.com)",
                    "credits": "from sicherlich, released July 3, 2020",
                    "license": "all rights reserved"
                }
            ]
        },
        {
            "url": "https://axeldoerner.bandcamp.com/album/the-beauty-of-exaggeration",
            "title": "The Beauty of Exaggeration",
            "artist": "Petr Vrba, Ivan Palacký, Axel Dörner",
            "label": null,
            "band_id": 1365097893,
            "classification": "paid",
            "tags": [
                "Jazz"
            ],
            "item_id": 3422255916,
            "art_id": 357935352,
            "is_preorder": false,
            "datePublished": "10 Apr 2020 19:43:38 GMT",
            "about": "Axel Dörner: trumpet, electronics\nIvan Palacký: Dopleta 180 amplified knitting machine\nPetr Vrba: trumpet, electronics\nPeter Graham: organ on Rattle Gatherers\nTrack 1 and 3 recorded in gallery mimokolektiv by Václav Hruška on 20.11.2017, Olomouc, Czech Republic\nTrack 2 recorded at Husův sbor by Ladislav Mirvis Mirvald on 19.11.2017, Brno, Czech Republic\nthanks to AVA collective, Sandra Silná, Ladislav Mirvis Mirvald, Jakub Frank, mimokolektiv,  Martin Klimeš, Jaroslav Bašta, Punctum, Divadlo 29, Zdeněk Závodný, Václav Hruška",
            "credits": "released April 10, 2020\nPetr Vrba, Ivan Palacký, Axel Dörner",
            "license": "all rights reserved",
            "coverUrl_0": "https://f4.bcbits.com/img/a0357935352_0",
            "trackinfo": [
                {
                    "title": "The Beauty of Exaggeration",
                    "duration": "18:17",
                    "lyrics": null,
                    "label": null,
                    "track_id": 2766916083,
                    "track_num": "1",
                    "artist": "Petr Vrba, Ivan Palacký, Axel Dörner",
                    "url": "https://axeldoerner.bandcamp.com/track/the-beauty-of-exaggeration",
                    "trackCoverUrl_0": "https://f4.bcbits.com/img/a0357935352_0",
                    "art_id": 357935352,
                    "about": "Axel Dörner: trumpet, electronics\nIvan Palacký: Dopleta 180 amplified knitting machine\nPetr Vrba: trumpet, electronics\nrecorded in gallery mimokolektiv by Václav Hruška on 20.11.2017, Olomouc, Czech Republic",
                    "credits": "from The Beauty of Exaggeration, released April 10, 2020\nPetr Vrba, Ivan Palacký, Axel Dörner",
                    "license": "all rights reserved"
                },
                {
                    "title": "Rattle Gatherers",
                    "duration": "20:09",
                    "lyrics": null,
                    "label": null,
                    "track_id": 718347148,
                    "track_num": "2",
                    "artist": "Petr Vrba, Ivan Palacký, Axel Dörner",
                    "url": "https://axeldoerner.bandcamp.com/track/rattle-gatherers",
                    "trackCoverUrl_0": "https://f4.bcbits.com/img/a0357935352_0",
                    "art_id": 357935352,
                    "about": "Axel Dörner: trumpet, electronics\nIvan Palacký: Dopleta 180 amplified knitting machine\nPetr Vrba: trumpet, electronics\nPeter Graham: organ\nrecorded at Husův sbor by Ladislav Mirvis Mirvald on 19.11.2017, Brno, Czech Republic",
                    "credits": "from The Beauty of Exaggeration, released April 10, 2020\nPetr Vrba, Ivan Palacký, Axel Dörner, Peter Graham",
                    "license": "all rights reserved"
                },
                {
                    "title": "Brushwood Collectors",
                    "duration": "22:44",
                    "lyrics": null,
                    "label": null,
                    "track_id": 625129213,
                    "track_num": "3",
                    "artist": "Petr Vrba, Ivan Palacký, Axel Dörner",
                    "url": "https://axeldoerner.bandcamp.com/track/brushwood-collectors",
                    "trackCoverUrl_0": "https://f4.bcbits.com/img/a0357935352_0",
                    "art_id": 357935352,
                    "about": "Axel Dörner: trumpet, electronics\nIvan Palacký: Dopleta 180 amplified knitting machine\nPetr Vrba: trumpet, electronics\nrecorded in gallery mimokolektiv by Václav Hruška on 20.11.2017, Olomouc, Czech Republic",
                    "credits": "from The Beauty of Exaggeration, released April 10, 2020\nPetr Vrba, Ivan Palacký, Axel Dörner",
                    "license": "all rights reserved"
                }
            ]
        },
        {
            "url": "https://axeldoerner.bandcamp.com/album/the-streetfighters-quartet",
            "title": "The Streetfighters Quartet",
            "artist": "The Streetfighters",
            "label": null,
            "band_id": 1365097893,
            "classification": "paid",
            "tags": [
                "Jazz"
            ],
            "item_id": 3517172005,
            "art_id": 3984868221,
            "is_preorder": false,
            "datePublished": "10 Apr 2020 19:13:15 GMT",
            "about": "Bruno Leicht trumpet (left channel)\nAxel Dörner trumpet (right channel)\nJan Roder bass\nMichael Griener drums\nRecorded by Rainer Robben, Audio Cue\nBerlin, July 23, 2001\nMixed & mastered by The Streetfighters",
            "credits": "released April 10, 2020\nThe Streetfighters",
            "license": "all rights reserved",
            "coverUrl_0": "https://f4.bcbits.com/img/a3984868221_0",
            "trackinfo": [
                {
                    "title": "One Up-Ballad (Bruno Leicht)",
                    "duration": "07:19",
                    "lyrics": null,
                    "label": null,
                    "track_id": 1538773047,
                    "track_num": "1",
                    "artist": "The Streetfighters",
                    "url": "https://axeldoerner.bandcamp.com/track/one-up-ballad-bruno-leicht",
                    "trackCoverUrl_0": "https://f4.bcbits.com/img/a3984868221_0",
                    "art_id": 3984868221,
                    "about": "Bruno Leicht trumpet (left channel)\nAxel Dörner trumpet (right channel)\nJan Roder bass\nMichael Griener drums\nRecorded by Rainer Robben, Audio Cue\nBerlin, July 23, 2001\nMixed & mastered by The Streetfighters",
                    "credits": "from The Streetfighters Quartet, released April 10, 2020\nBruno Leicht",
                    "license": "all rights reserved"
                },
                {
                    "title": "Umsicht (Axel Dörner)",
                    "duration": "04:44",
                    "lyrics": null,
                    "label": null,
                    "track_id": 628272360,
                    "track_num": "2",
                    "artist": "The Streetfighters",
                    "url": "https://axeldoerner.bandcamp.com/track/umsicht-axel-d-rner",
                    "trackCoverUrl_0": "https://f4.bcbits.com/img/a3984868221_0",
                    "art_id": 3984868221,
                    "about": "Bruno Leicht trumpet (left channel)\nAxel Dörner trumpet (right channel)\nJan Roder bass\nMichael Griener drums\nRecorded by Rainer Robben, Audio Cue\nBerlin, July 23, 2001\nMixed & mastered by The Streetfighters",
                    "credits": "from The Streetfighters Quartet, released April 10, 2020\nAxel Dörner",
                    "license": "all rights reserved"
                },
                {
                    "title": "Statement, No Questions Asked (Bruno Leicht)",
                    "duration": "03:11",
                    "lyrics": null,
                    "label": null,
                    "track_id": 206183282,
                    "track_num": "3",
                    "artist": "The Streetfighters",
                    "url": "https://axeldoerner.bandcamp.com/track/statement-no-questions-asked-bruno-leicht",
                    "trackCoverUrl_0": "https://f4.bcbits.com/img/a3984868221_0",
                    "art_id": 3984868221,
                    "about": "Bruno Leicht trumpet (left channel)\nAxel Dörner trumpet (right channel)\nJan Roder bass\nMichael Griener drums\nRecorded by Rainer Robben, Audio Cue\nBerlin, July 23, 2001\nMixed & mastered by The Streetfighters",
                    "credits": "from The Streetfighters Quartet, released April 10, 2020\nBruno Leicht",
                    "license": "all rights reserved"
                },
                {
                    "title": "Just Squeeze Me (But Please Don't Tease Me) (Subtle Slough)  (Duke Ellington - Lee Gaines)",
                    "duration": "04:45",
                    "lyrics": null,
                    "label": null,
                    "track_id": 496736460,
                    "track_num": "4",
                    "artist": "The Streetfighters",
                    "url": "https://axeldoerner.bandcamp.com/track/just-squeeze-me-but-please-dont-tease-me-subtle-slough-duke-ellington-lee-gaines",
                    "trackCoverUrl_0": "https://f4.bcbits.com/img/a3984868221_0",
                    "art_id": 3984868221,
                    "about": "Bruno Leicht trumpet (left channel)\nAxel Dörner trumpet (right channel)\nJan Roder bass\nMichael Griener drums\nRecorded by Rainer Robben, Audio Cue\nBerlin, July 23, 2001\nMixed & mastered by The Streetfighters",
                    "credits": "from The Streetfighters Quartet, released April 10, 2020\nDuke Ellington - Lee Gaines",
                    "license": "all rights reserved"
                },
                {
                    "title": "Die Armen (Bruno Leicht)",
                    "duration": "02:19",
                    "lyrics": null,
                    "label": null,
                    "track_id": 2842491796,
                    "track_num": "5",
                    "artist": "The Streetfighters",
                    "url": "https://axeldoerner.bandcamp.com/track/die-armen-bruno-leicht",
                    "trackCoverUrl_0": "https://f4.bcbits.com/img/a3984868221_0",
                    "art_id": 3984868221,
                    "about": "Bruno Leicht trumpet (left channel)\nAxel Dörner trumpet (right channel)\nJan Roder bass\nMichael Griener drums\nRecorded by Rainer Robben, Audio Cue\nBerlin, July 23, 2001\nMixed & mastered by The Streetfighters",
                    "credits": "from The Streetfighters Quartet, released April 10, 2020\nBruno Leicht",
                    "license": "all rights reserved"
                },
                {
                    "title": "Abversicht (Axel Dörner)",
                    "duration": "04:56",
                    "lyrics": null,
                    "label": null,
                    "track_id": 1068627440,
                    "track_num": "6",
                    "artist": "The Streetfighters",
                    "url": "https://axeldoerner.bandcamp.com/track/abversicht-axel-d-rner",
                    "trackCoverUrl_0": "https://f4.bcbits.com/img/a3984868221_0",
                    "art_id": 3984868221,
                    "about": "Bruno Leicht trumpet (left channel)\nAxel Dörner trumpet (right channel)\nJan Roder bass\nMichael Griener drums\nRecorded by Rainer Robben, Audio Cue\nBerlin, July 23, 2001\nMixed & mastered by The Streetfighters",
                    "credits": "from The Streetfighters Quartet, released April 10, 2020\nAxel Dörner",
                    "license": "all rights reserved"
                },
                {
                    "title": "Lover Man (Jimmy Davis - Ram Ramirez - Jimmy Sherman)",
                    "duration": "04:57",
                    "lyrics": null,
                    "label": null,
                    "track_id": 2195766615,
                    "track_num": "7",
                    "artist": "The Streetfighters",
                    "url": "https://axeldoerner.bandcamp.com/track/lover-man-jimmy-davis-ram-ramirez-jimmy-sherman",
                    "trackCoverUrl_0": "https://f4.bcbits.com/img/a3984868221_0",
                    "art_id": 3984868221,
                    "about": "Bruno Leicht trumpet (left channel)\nAxel Dörner trumpet (right channel)\nJan Roder bass\nMichael Griener drums\nRecorded by Rainer Robben, Audio Cue\nBerlin, July 23, 2001\nMixed & mastered by The Streetfighters",
                    "credits": "from The Streetfighters Quartet, released April 10, 2020\nJimmy Davis - Ram Ramirez - Jimmy Sherman",
                    "license": "all rights reserved"
                },
                {
                    "title": "Der Hypochonder (Bruno Leicht)",
                    "duration": "02:14",
                    "lyrics": null,
                    "label": null,
                    "track_id": 2725964307,
                    "track_num": "8",
                    "artist": "The Streetfighters",
                    "url": "https://axeldoerner.bandcamp.com/track/der-hypochonder-bruno-leicht",
                    "trackCoverUrl_0": "https://f4.bcbits.com/img/a3984868221_0",
                    "art_id": 3984868221,
                    "about": "Bruno Leicht trumpet (left channel)\nAxel Dörner trumpet (right channel)\nJan Roder bass\nMichael Griener drums\nRecorded by Rainer Robben, Audio Cue\nBerlin, July 23, 2001\nMixed & mastered by The Streetfighters",
                    "credits": "from The Streetfighters Quartet, released April 10, 2020\nBruno Leicht",
                    "license": "all rights reserved"
                },
                {
                    "title": "Royal Garden Blues (Clarence Williams - Spencer Williams)",
                    "duration": "04:35",
                    "lyrics": null,
                    "label": null,
                    "track_id": 3675662985,
                    "track_num": "9",
                    "artist": "The Streetfighters",
                    "url": "https://axeldoerner.bandcamp.com/track/royal-garden-blues-clarence-williams-spencer-williams",
                    "trackCoverUrl_0": "https://f4.bcbits.com/img/a3984868221_0",
                    "art_id": 3984868221,
                    "about": "Bruno Leicht trumpet (left channel)\nAxel Dörner trumpet (right channel)\nJan Roder bass\nMichael Griener drums\nRecorded by Rainer Robben, Audio Cue\nBerlin, July 23, 2001\nMixed & mastered by The Streetfighters",
                    "credits": "from The Streetfighters Quartet, released April 10, 2020\nClarence Williams - Spencer Williams",
                    "license": "all rights reserved"
                },
                {
                    "title": "The Moon Of Manakoora       (from the 1937 Paramount film production \"The Hurricane\") (Frank Loesser - Alfred Newman)",
                    "duration": "06:22",
                    "lyrics": null,
                    "label": null,
                    "track_id": 3512020752,
                    "track_num": "10",
                    "artist": "The Streetfighters",
                    "url": "https://axeldoerner.bandcamp.com/track/the-moon-of-manakoora-from-the-1937-paramount-film-production-the-hurricane-frank-loesser-alfred-newman",
                    "trackCoverUrl_0": "https://f4.bcbits.com/img/a3984868221_0",
                    "art_id": 3984868221,
                    "about": "Bruno Leicht trumpet (left channel)\nAxel Dörner trumpet (right channel)\nJan Roder bass\nMichael Griener drums\nRecorded by Rainer Robben, Audio Cue\nBerlin, July 23, 2001\nMixed & mastered by The Streetfighters",
                    "credits": "from The Streetfighters Quartet, released April 10, 2020\nFrank Loesser - Alfred Newman",
                    "license": "all rights reserved"
                },
                {
                    "title": "Thie Moudivaedor (Axel Dörner)",
                    "duration": "02:47",
                    "lyrics": null,
                    "label": null,
                    "track_id": 844264415,
                    "track_num": "11",
                    "artist": "The Streetfighters",
                    "url": "https://axeldoerner.bandcamp.com/track/thie-moudivaedor-axel-d-rner",
                    "trackCoverUrl_0": "https://f4.bcbits.com/img/a3984868221_0",
                    "art_id": 3984868221,
                    "about": "Bruno Leicht trumpet (left channel)\nAxel Dörner trumpet (right channel)\nJan Roder bass\nMichael Griener drums\nRecorded by Rainer Robben, Audio Cue\nBerlin, July 23, 2001\nMixed & mastered by The Streetfighters",
                    "credits": "from The Streetfighters Quartet, released April 10, 2020\nAxel Dörner",
                    "license": "all rights reserved"
                },
                {
                    "title": "When It's Sleepy Time Down South       (from the 1931 Warner Bros. film production \"Safe In Hell\")       (Clarence Muse - Leon René - Otis René)",
                    "duration": "04:28",
                    "lyrics": null,
                    "label": null,
                    "track_id": 3912678351,
                    "track_num": "12",
                    "artist": "The Streetfighters",
                    "url": "https://axeldoerner.bandcamp.com/track/when-its-sleepy-time-down-south-from-the-1931-warner-bros-film-production-safe-in-hell-clarence-muse-leon-ren-otis-ren",
                    "trackCoverUrl_0": "https://f4.bcbits.com/img/a3984868221_0",
                    "art_id": 3984868221,
                    "about": "Bruno Leicht trumpet (left channel)\nAxel Dörner trumpet (right channel)\nJan Roder bass\nMichael Griener drums\nRecorded by Rainer Robben, Audio Cue\nBerlin, July 23, 2001\nMixed & mastered by The Streetfighters",
                    "credits": "from The Streetfighters Quartet, released April 10, 2020\nClarence Muse - Leon René - Otis René",
                    "license": "all rights reserved"
                },
                {
                    "title": "Thie Moudivaedor II (T.M. II) (Bruno Leicht)",
                    "duration": "03:58",
                    "lyrics": null,
                    "label": null,
                    "track_id": 267993529,
                    "track_num": "13",
                    "artist": "The Streetfighters",
                    "url": "https://axeldoerner.bandcamp.com/track/thie-moudivaedor-ii-t-m-ii-bruno-leicht",
                    "trackCoverUrl_0": "https://f4.bcbits.com/img/a3984868221_0",
                    "art_id": 3984868221,
                    "about": "Bruno Leicht trumpet (left channel)\nAxel Dörner trumpet (right channel)\nJan Roder bass\nMichael Griener drums\nRecorded by Rainer Robben, Audio Cue\nBerlin, July 23, 2001\nMixed & mastered by The Streetfighters",
                    "credits": "from The Streetfighters Quartet, released April 10, 2020\nBruno Leicht",
                    "license": "all rights reserved"
                }
            ]
        },
        {
            "url": "https://axeldoerner.bandcamp.com/album/unbar",
            "title": "unbar",
            "artist": "Axel Dörner",
            "label": null,
            "band_id": 1365097893,
            "classification": "paid",
            "tags": [
                "Jazz"
            ],
            "item_id": 1263747758,
            "art_id": 78727400,
            "is_preorder": false,
            "datePublished": "01 Aug 2025 20:05:49 GMT",
            "about": null,
            "credits": "released August 1, 2025\nAxel Dörner trumpet, electronics\nrecorded April 2025 in Berlin, Germany",
            "license": "all rights reserved",
            "coverUrl_0": "https://f4.bcbits.com/img/a0078727400_0",
            "trackinfo": [
                {
                    "title": "denkbar",
                    "duration": "14:46",
                    "lyrics": null,
                    "label": null,
                    "track_id": 3376395270,
                    "track_num": "1",
                    "artist": "Axel Dörner",
                    "url": "https://axeldoerner.bandcamp.com/track/denkbar",
                    "trackCoverUrl_0": "https://f4.bcbits.com/img/a0078727400_0",
                    "art_id": 78727400,
                    "about": null,
                    "credits": "from unbar, released August 1, 2025\nAxel Dörner trumpet, electronics\nrecorded April 2025 in Berlin, Germany",
                    "license": "all rights reserved"
                },
                {
                    "title": "vorstellbar",
                    "duration": "27:24",
                    "lyrics": null,
                    "label": null,
                    "track_id": 3108181356,
                    "track_num": "2",
                    "artist": "Axel Dörner",
                    "url": "https://axeldoerner.bandcamp.com/track/vorstellbar",
                    "trackCoverUrl_0": "https://f4.bcbits.com/img/a0078727400_0",
                    "art_id": 78727400,
                    "about": null,
                    "credits": "from unbar, released August 1, 2025\nAxel Dörner trumpet, electronics\nrecorded April 2025 in Berlin, Germany",
                    "license": "all rights reserved"
                },
                {
                    "title": "unfassbar",
                    "duration": "27:23",
                    "lyrics": null,
                    "label": null,
                    "track_id": 844108987,
                    "track_num": "3",
                    "artist": "Axel Dörner",
                    "url": "https://axeldoerner.bandcamp.com/track/unfassbar",
                    "trackCoverUrl_0": "https://f4.bcbits.com/img/a0078727400_0",
                    "art_id": 78727400,
                    "about": null,
                    "credits": "from unbar, released August 1, 2025\nAxel Dörner trumpet, electronics\nrecorded April 2025 in Berlin, Germany",
                    "license": "all rights reserved"
                }
            ]
        },
        {
            "url": "https://axeldoerner.bandcamp.com/album/untitled",
            "title": "Untitled",
            "artist": "Axel Dörner",
            "label": null,
            "band_id": 1365097893,
            "classification": "paid",
            "tags": [
                "Jazz"
            ],
            "item_id": 3403007757,
            "art_id": 2601034146,
            "is_preorder": false,
            "datePublished": "10 Apr 2020 20:01:28 GMT",
            "about": "Axel Dörner — trumpet\nrecorded 1998 in Berlin\n(previously released as CD-R)",
            "credits": "released April 10, 2020\nAxel Dörner",
            "license": "all rights reserved",
            "coverUrl_0": "https://f4.bcbits.com/img/a2601034146_0",
            "trackinfo": [
                {
                    "title": "1........07.33",
                    "duration": "07:33",
                    "lyrics": null,
                    "label": null,
                    "track_id": 20921446,
                    "track_num": "1",
                    "artist": "Axel Dörner",
                    "url": "https://axeldoerner.bandcamp.com/track/1-0733",
                    "trackCoverUrl_0": "https://f4.bcbits.com/img/a2601034146_0",
                    "art_id": 2601034146,
                    "about": "Axel Dörner — trumpet\nrecorded 1998 in Berlin",
                    "credits": "from Untitled, released April 10, 2020\nAxel Dörner",
                    "license": "all rights reserved"
                },
                {
                    "title": "2........17.35",
                    "duration": "17:35",
                    "lyrics": null,
                    "label": null,
                    "track_id": 3352503028,
                    "track_num": "2",
                    "artist": "Axel Dörner",
                    "url": "https://axeldoerner.bandcamp.com/track/2-1735",
                    "trackCoverUrl_0": "https://f4.bcbits.com/img/a2601034146_0",
                    "art_id": 2601034146,
                    "about": "Axel Dörner — trumpet\nrecorded 1998 in Berlin",
                    "credits": "from Untitled, released April 10, 2020\nAxel Dörner",
                    "license": "all rights reserved"
                }
            ]
        },
        {
            "url": "https://axeldoerner.bandcamp.com/album/untitled-2",
            "title": "Untitled",
            "artist": "Axel Dörner",
            "label": null,
            "band_id": 1365097893,
            "classification": "paid",
            "tags": [
                "Jazz"
            ],
            "item_id": 3903149994,
            "art_id": 2401365015,
            "is_preorder": false,
            "datePublished": "10 Apr 2020 20:09:36 GMT",
            "about": "Axel Dörner — trumpet\nrecorded 1998 in Berlin\n(previously released as CD-R)",
            "credits": "released April 10, 2020\nAxel Dörner",
            "license": "all rights reserved",
            "coverUrl_0": "https://f4.bcbits.com/img/a2401365015_0",
            "trackinfo": [
                {
                    "title": "1........14.53",
                    "duration": "14:53",
                    "lyrics": null,
                    "label": null,
                    "track_id": 2123787096,
                    "track_num": "1",
                    "artist": "Axel Dörner",
                    "url": "https://axeldoerner.bandcamp.com/track/1-1453",
                    "trackCoverUrl_0": "https://f4.bcbits.com/img/a2401365015_0",
                    "art_id": 2401365015,
                    "about": "Axel Dörner — trumpet\nrecorded 1998 in Berlin",
                    "credits": "from Untitled, released April 10, 2020\nAxel Dörner",
                    "license": "all rights reserved"
                },
                {
                    "title": "2........11.11",
                    "duration": "11:11",
                    "lyrics": null,
                    "label": null,
                    "track_id": 611867277,
                    "track_num": "2",
                    "artist": "Axel Dörner",
                    "url": "https://axeldoerner.bandcamp.com/track/2-1111",
                    "trackCoverUrl_0": "https://f4.bcbits.com/img/a2401365015_0",
                    "art_id": 2401365015,
                    "about": "Axel Dörner — trumpet\nrecorded 1998 in Berlin",
                    "credits": "from Untitled, released April 10, 2020\nAxel Dörner",
                    "license": "all rights reserved"
                }
            ]
        },
        {
            "url": "https://axeldoerner.bandcamp.com/album/untitled-3",
            "title": "Untitled",
            "artist": "Axel Dörner",
            "label": null,
            "band_id": 1365097893,
            "classification": "paid",
            "tags": [
                "Jazz"
            ],
            "item_id": 3882884319,
            "art_id": 714759742,
            "is_preorder": false,
            "datePublished": "10 Apr 2020 20:27:44 GMT",
            "about": "Axel Dörner — trumpet\nrecorded January 2000 in Berlin\n(previously released as CD-R)",
            "credits": "released April 10, 2020\nAxel Dörner",
            "license": "all rights reserved",
            "coverUrl_0": "https://f4.bcbits.com/img/a0714759742_0",
            "trackinfo": [
                {
                    "title": "1........11.21",
                    "duration": "11:21",
                    "lyrics": null,
                    "label": null,
                    "track_id": 1161287982,
                    "track_num": "1",
                    "artist": "Axel Dörner",
                    "url": "https://axeldoerner.bandcamp.com/track/1-1121",
                    "trackCoverUrl_0": "https://f4.bcbits.com/img/a0714759742_0",
                    "art_id": 714759742,
                    "about": "Axel Dörner — trumpet\nrecorded January 2000 in Berlin",
                    "credits": "from Untitled, released April 10, 2020\nAxel Dörner",
                    "license": "all rights reserved"
                },
                {
                    "title": "2........07.19",
                    "duration": "07:19",
                    "lyrics": null,
                    "label": null,
                    "track_id": 3275496230,
                    "track_num": "2",
                    "artist": "Axel Dörner",
                    "url": "https://axeldoerner.bandcamp.com/track/2-0719",
                    "trackCoverUrl_0": "https://f4.bcbits.com/img/a0714759742_0",
                    "art_id": 714759742,
                    "about": "Axel Dörner — trumpet\nrecorded January 2000 in Berlin",
                    "credits": "from Untitled, released April 10, 2020\nAxel Dörner",
                    "license": "all rights reserved"
                },
                {
                    "title": "3........13.10",
                    "duration": "13:10",
                    "lyrics": null,
                    "label": null,
                    "track_id": 3216427195,
                    "track_num": "3",
                    "artist": "Axel Dörner",
                    "url": "https://axeldoerner.bandcamp.com/track/3-1310",
                    "trackCoverUrl_0": "https://f4.bcbits.com/img/a0714759742_0",
                    "art_id": 714759742,
                    "about": "Axel Dörner — trumpet\nrecorded January 2000 in Berlin",
                    "credits": "from Untitled, released April 10, 2020\nAxel Dörner",
                    "license": "all rights reserved"
                },
                {
                    "title": "4........09.36",
                    "duration": "09:36",
                    "lyrics": null,
                    "label": null,
                    "track_id": 2526375551,
                    "track_num": "4",
                    "artist": "Axel Dörner",
                    "url": "https://axeldoerner.bandcamp.com/track/4-0936",
                    "trackCoverUrl_0": "https://f4.bcbits.com/img/a0714759742_0",
                    "art_id": 714759742,
                    "about": "Axel Dörner — trumpet\nrecorded January 2000 in Berlin",
                    "credits": "from Untitled, released April 10, 2020\nAxel Dörner",
                    "license": "all rights reserved"
                },
                {
                    "title": "5........14.23",
                    "duration": "14:23",
                    "lyrics": null,
                    "label": null,
                    "track_id": 391745759,
                    "track_num": "5",
                    "artist": "Axel Dörner",
                    "url": "https://axeldoerner.bandcamp.com/track/5-1423",
                    "trackCoverUrl_0": "https://f4.bcbits.com/img/a0714759742_0",
                    "art_id": 714759742,
                    "about": "Axel Dörner — trumpet\nrecorded January 2000 in Berlin",
                    "credits": "from Untitled, released April 10, 2020\nAxel Dörner",
                    "license": "all rights reserved"
                }
            ]
        },
        {
            "url": "https://axeldoerner.bandcamp.com/album/unweil",
            "title": "unweil",
            "artist": "Axel Dörner",
            "label": null,
            "band_id": 1365097893,
            "classification": "paid",
            "tags": [
                "Jazz"
            ],
            "item_id": 4160572480,
            "art_id": 2064021876,
            "is_preorder": false,
            "datePublished": "03 Aug 2023 23:30:32 GMT",
            "about": "Axel Dörner — trumpet, electronics\nrecorded on 14th of March 2023 in Berlin",
            "credits": "released August 3, 2023",
            "license": "all rights reserved",
            "coverUrl_0": "https://f4.bcbits.com/img/a2064021876_0",
            "trackinfo": [
                {
                    "title": "unweil",
                    "duration": "39:34",
                    "lyrics": null,
                    "label": null,
                    "track_id": 1655995854,
                    "track_num": "1",
                    "artist": "Axel Dörner",
                    "url": "https://axeldoerner.bandcamp.com/track/unweil",
                    "trackCoverUrl_0": "https://f4.bcbits.com/img/a2064021876_0",
                    "art_id": 2064021876,
                    "about": "Axel Dörner — trumpet, electronics\nrecorded on 14th of March 2023 in Berlin",
                    "credits": "from unweil, released August 3, 2023",
                    "license": "all rights reserved"
                }
            ]
        },
        {
            "url": "https://axeldoerner.bandcamp.com/album/unzusicht-1738",
            "title": "unzusicht 17.38",
            "artist": "Axel Dörner",
            "label": null,
            "band_id": 1365097893,
            "classification": "paid",
            "tags": [
                "Jazz"
            ],
            "item_id": 1646828583,
            "art_id": 2756965349,
            "is_preorder": false,
            "datePublished": "28 May 2020 00:00:00 GMT",
            "about": "Axel Dörner trumpet, electronics\nrecorded May 2020 in Berlin",
            "credits": "released May 28, 2020\nAxel Dörner",
            "license": "all rights reserved",
            "coverUrl_0": "https://f4.bcbits.com/img/a2756965349_0",
            "trackinfo": [
                {
                    "title": "unzusicht 17.38",
                    "duration": "17:38",
                    "lyrics": null,
                    "label": null,
                    "track_id": 1278050407,
                    "track_num": "1",
                    "artist": "Axel Dörner",
                    "url": "https://axeldoerner.bandcamp.com/track/unzusicht-1738",
                    "trackCoverUrl_0": "https://f4.bcbits.com/img/a2756965349_0",
                    "art_id": 2756965349,
                    "about": null,
                    "credits": "from unzusicht 17.38, released May 28, 2020",
                    "license": "all rights reserved"
                }
            ]
        },
        {
            "url": "https://axeldoerner.bandcamp.com/album/unzusicht-2318",
            "title": "unzusicht 23.18",
            "artist": "Axel Dörner",
            "label": null,
            "band_id": 1365097893,
            "classification": "paid",
            "tags": [
                "Jazz"
            ],
            "item_id": 1899691156,
            "art_id": 692643315,
            "is_preorder": false,
            "datePublished": "28 May 2020 00:00:00 GMT",
            "about": "Axel Dörner trumpet, electronics\nrecorded May 2020 in Berlin",
            "credits": "released May 28, 2020\nAxel Dörner",
            "license": "all rights reserved",
            "coverUrl_0": "https://f4.bcbits.com/img/a0692643315_0",
            "trackinfo": [
                {
                    "title": "unzusicht 23.18",
                    "duration": "23:18",
                    "lyrics": null,
                    "label": null,
                    "track_id": 2313471515,
                    "track_num": "1",
                    "artist": "Axel Dörner",
                    "url": "https://axeldoerner.bandcamp.com/track/unzusicht-2318",
                    "trackCoverUrl_0": "https://f4.bcbits.com/img/a3197446780_0",
                    "art_id": 3197446780,
                    "about": "Axel Dörner trumpet, electronics\nrecorded in Berlin in May 2020",
                    "credits": "from unzusicht 23.18, released May 28, 2020\nAxel Dörner",
                    "license": "all rights reserved"
                }
            ]
        },
        {
            "url": "https://axeldoerner.bandcamp.com/album/unzusicht-2634-2",
            "title": "unzusicht 26.34",
            "artist": "Axel Dörner",
            "label": null,
            "band_id": 1365097893,
            "classification": "paid",
            "tags": [
                "Jazz"
            ],
            "item_id": 652240983,
            "art_id": 1556382867,
            "is_preorder": false,
            "datePublished": "28 May 2020 00:00:00 GMT",
            "about": "Axel Dörner trumpet, electronics\nrecorded in May 2020 in Berlin",
            "credits": "released May 28, 2020\nAxel Dörner",
            "license": "all rights reserved",
            "coverUrl_0": "https://f4.bcbits.com/img/a1556382867_0",
            "trackinfo": [
                {
                    "title": "unzusicht 26.34",
                    "duration": "26:34",
                    "lyrics": null,
                    "label": null,
                    "track_id": 2119051342,
                    "track_num": "1",
                    "artist": "Axel Dörner",
                    "url": "https://axeldoerner.bandcamp.com/track/unzusicht-2634",
                    "trackCoverUrl_0": "https://f4.bcbits.com/img/a1556382867_0",
                    "art_id": 1556382867,
                    "about": null,
                    "credits": "from unzusicht 26.34, released May 28, 2020",
                    "license": "all rights reserved"
                }
            ]
        },
        {
            "url": "https://axeldoerner.bandcamp.com/album/unzusicht-2743",
            "title": "unzusicht 27.43",
            "artist": "Axel Dörner",
            "label": null,
            "band_id": 1365097893,
            "classification": "paid",
            "tags": [
                "Jazz"
            ],
            "item_id": 3794059450,
            "art_id": 3703227968,
            "is_preorder": false,
            "datePublished": "28 May 2020 00:11:42 GMT",
            "about": "Axel Dörner trumpet, electronics\nrecorded in Berlin in May 2020",
            "credits": "released May 28, 2020",
            "license": "all rights reserved",
            "coverUrl_0": "https://f4.bcbits.com/img/a3703227968_0",
            "trackinfo": [
                {
                    "title": "unzusicht 27.43",
                    "duration": "27:43",
                    "lyrics": null,
                    "label": null,
                    "track_id": 2563559728,
                    "track_num": "1",
                    "artist": "Axel Dörner",
                    "url": "https://axeldoerner.bandcamp.com/track/unzusicht-2743",
                    "trackCoverUrl_0": "https://f4.bcbits.com/img/a3703227968_0",
                    "art_id": 3703227968,
                    "about": "Axel Dörner trumpet, electronics\nrecorded May 2020 in Berlin",
                    "credits": "from unzusicht 27.43, track released May 28, 2020\nAxel Dörner",
                    "license": "all rights reserved"
                }
            ]
        },
        {
            "url": "https://axeldoerner.bandcamp.com/album/unzusicht-2923-2",
            "title": "unzusicht 29.23",
            "artist": "Axel Dörner",
            "label": null,
            "band_id": 1365097893,
            "classification": "paid",
            "tags": [
                "Jazz"
            ],
            "item_id": 3330404532,
            "art_id": 2882929008,
            "is_preorder": false,
            "datePublished": "28 May 2020 00:00:00 GMT",
            "about": "Axel Dörner trumpet, electronics\nrecorded May 2020 in Berlin",
            "credits": "released May 28, 2020\nAxel Dörner",
            "license": "all rights reserved",
            "coverUrl_0": "https://f4.bcbits.com/img/a2882929008_0",
            "trackinfo": [
                {
                    "title": "unzusicht 29.23",
                    "duration": "29:23",
                    "lyrics": null,
                    "label": null,
                    "track_id": 1702151359,
                    "track_num": "1",
                    "artist": "Axel Dörner",
                    "url": "https://axeldoerner.bandcamp.com/track/unzusicht-2923",
                    "trackCoverUrl_0": "https://f4.bcbits.com/img/a2882929008_0",
                    "art_id": 2882929008,
                    "about": null,
                    "credits": "from unzusicht 29.23, released May 28, 2020",
                    "license": "all rights reserved"
                }
            ]
        },
        {
            "url": "https://axeldoerner.bandcamp.com/album/wirksam",
            "title": "wirksam",
            "artist": "Niklas Fite / Axel Dörner",
            "label": null,
            "band_id": 1365097893,
            "classification": "paid",
            "tags": [
                "Jazz"
            ],
            "item_id": 970040783,
            "art_id": 1753794194,
            "is_preorder": false,
            "datePublished": "04 Oct 2024 00:00:00 GMT",
            "about": "Niklas Fite - guitar, banjo\nAxel Dörner - trumpet, electronics\nrecorded 2nd of February 2019 in Berlin at Studio Boerne\nmixed and mastered by Axel Dörner\nspecial thanks to Alexander Frangenheim",
            "credits": "released October 4, 2024",
            "license": "all rights reserved",
            "coverUrl_0": "https://f4.bcbits.com/img/a1753794194_0",
            "trackinfo": [
                {
                    "title": "haftbar",
                    "duration": "23:16",
                    "lyrics": null,
                    "label": null,
                    "track_id": 1487825309,
                    "track_num": "1",
                    "artist": "Niklas Fite / Axel Dörner",
                    "url": "https://axeldoerner.bandcamp.com/track/haftbar",
                    "trackCoverUrl_0": "https://f4.bcbits.com/img/a1441728189_0",
                    "art_id": 1441728189,
                    "about": "Niklas Fite - guitar, banjo\nAxel Dörner - trumpet, electronics\nrecorded 2nd of February 2019 in Berlin at Studio Boerne\nmixed and mastered by Axel Dörner",
                    "credits": "from wirksam, released October 4, 2024",
                    "license": "all rights reserved"
                },
                {
                    "title": "haltlos",
                    "duration": "26:40",
                    "lyrics": null,
                    "label": null,
                    "track_id": 3421500676,
                    "track_num": "2",
                    "artist": "Niklas Fite / Axel Dörner",
                    "url": "https://axeldoerner.bandcamp.com/track/haltlos",
                    "trackCoverUrl_0": "https://f4.bcbits.com/img/a1880856660_0",
                    "art_id": 1880856660,
                    "about": "Niklas Fite - guitar, banjo\nAxel Dörner - trumpet, electronics\nrecorded 2nd of February 2019 in Berlin at Studio Boerne\nmixed and mastered by Axel Dörner",
                    "credits": "from wirksam, released October 4, 2024",
                    "license": "all rights reserved"
                }
            ]
        },
        {
            "url": "https://axeldoerner.bandcamp.com/track/gegenfall",
            "title": "gegenfall",
            "artist": "Axel Dörner",
            "label": null,
            "band_id": 1365097893,
            "classification": "paid",
            "tags": [
                "Axel Dörner",
                "Jazz",
                "electronic music",
                "trumpet"
            ],
            "item_id": 2833238902,
            "art_id": 3485998513,
            "is_preorder": null,
            "datePublished": "01 Apr 2017 18:49:35 GMT",
            "about": null,
            "credits": "released April 1, 2017\nAxel Dörner — trumpet, electronics\nrecorded 4th of March 2017 in Berlin\nmixed and mastered by Axel Dörner",
            "license": "all rights reserved",
            "coverUrl_0": "https://f4.bcbits.com/img/a3485998513_0",
            "trackinfo": [
                {
                    "title": "gegenfall",
                    "duration": "18:36",
                    "lyrics": null,
                    "label": null,
                    "track_id": 2833238902,
                    "track_num": "None",
                    "artist": "Axel Dörner",
                    "url": "https://axeldoerner.bandcamp.com/track/gegenfall",
                    "trackCoverUrl_0": "https://f4.bcbits.com/img/a3485998513_0",
                    "art_id": 3485998513,
                    "about": null,
                    "credits": "released April 1, 2017\nAxel Dörner — trumpet, electronics\nrecorded 4th of March 2017 in Berlin\nmixed and mastered by Axel Dörner",
                    "license": "all rights reserved"
                }
            ]
        },
        {
            "url": "https://axeldoerner.bandcamp.com/track/vorfall",
            "title": "vorfall",
            "artist": "Axel Dörner",
            "label": null,
            "band_id": 1365097893,
            "classification": "paid",
            "tags": [
                "Axel Dörner",
                "Jazz",
                "electronic music",
                "trumpet"
            ],
            "item_id": 2473326655,
            "art_id": 884725867,
            "is_preorder": null,
            "datePublished": "01 Apr 2017 16:09:19 GMT",
            "about": null,
            "credits": "released April 1, 2017\nAxel Dörner — trumpet, electronics\nrecorded 3rd of March 2017 in Berlin\nmixed and mastered by Axel Dörner",
            "license": "all rights reserved",
            "coverUrl_0": "https://f4.bcbits.com/img/a0884725867_0",
            "trackinfo": [
                {
                    "title": "vorfall",
                    "duration": "32:46",
                    "lyrics": null,
                    "label": null,
                    "track_id": 2473326655,
                    "track_num": "None",
                    "artist": "Axel Dörner",
                    "url": "https://axeldoerner.bandcamp.com/track/vorfall",
                    "trackCoverUrl_0": "https://f4.bcbits.com/img/a0884725867_0",
                    "art_id": 884725867,
                    "about": null,
                    "credits": "released April 1, 2017\nAxel Dörner — trumpet, electronics\nrecorded 3rd of March 2017 in Berlin\nmixed and mastered by Axel Dörner",
                    "license": "all rights reserved"
                }
            ]
        }
    ],
    "_band_id": 1365097893
}